Workbook

Sheet Summary
A1: Healthcare chatbot evidence — analytical summary
A2: From User Experience to Organizational Value: A Critical Integrative Review of Intelligent Chatbots in Healthcare Services
A5: Historical analytical set | B5: Count | C5: Share | E5: Claim-level disposition | F5: Count | G5: Share
A6: Healthcare-specific reports | B6: =COUNTA('Core coding'!A5:A26) -> 22 | C6: =B6/$B$6 -> 1 | E6: Supported within tested conditions | F6: =COUNTIF('Claim dispositions'!$E$5:$E$22,E6) -> 2 | G6: =F6/$F$10 -> 0.11111111
A7: User measures | B7: =SUM('Core coding'!L5:L26) -> 22 | C7: =B7/$B$6 -> 1 | E7: Supported with qualifications | F7: =COUNTIF('Claim dispositions'!$E$5:$E$22,E7) -> 7 | G7: =F7/$F$10 -> 0.38888889
A8: Clinical measures | B8: =SUM('Core coding'!M5:M26) -> 11 | C8: =B8/$B$6 -> 0.5 | E8: Not established | F8: =COUNTIF('Claim dispositions'!$E$5:$E$22,E8) -> 7 | G8: =F8/$F$10 -> 0.38888889
A9: Referral-safety proxy | B9: =SUM('Core coding'!N5:N26) -> 1 | C9: =B9/$B$6 -> 0.045454545 | E9: Not assessed | F9: =COUNTIF('Claim dispositions'!$E$5:$E$22,E9) -> 2 | G9: =F9/$F$10 -> 0.11111111
A10: Health-system operations | B10: =SUM('Core coding'!Q5:Q26) -> 1 | C10: =B10/$B$6 -> 0.045454545 | E10: Total specified claims | F10: =COUNTA('Claim dispositions'!A5:A22) -> 18
A11: Patient productivity | B11: =SUM('Core coding'!R5:R26) -> 1 | C11: =B11/$B$6 -> 0.045454545 | E11: Worked cases | F11: =COUNTA('Worked cases'!A5:A13) -> 9
A12: Intervention-comparison family | B12: =SUM('Core coding'!K5:K26) -> 7 | C12: =B12/$B$6 -> 0.31818182
A13: Mental health and well-being | B13: =COUNTIF('Core coding'!E5:E26,"Mental health and well-being") -> 13 | C13: =B13/$B$6 -> 0.59090909
A16: Targeted source checks | B16: Count | C16: Access / scope | E16: Reading guide
A17: Historical reports | B17: =COUNTIF('Source checks'!$A$5:$A$33,"S01")+COUNTIF('Source checks'!$A$5:$A$33,"S02")+COUNTIF('Source checks'!$A$5:$A$33,"S03")+COUNTIF('Source checks'!$A$5:$A$33,"S04")+COUNTIF('Source checks'!$A$5:$A$33,"S05")+COUNTIF('Source checks'!$A$5:$A$33,"S08")+COUNTIF('Source checks'!$A$5:$A$33,"S09")+COUNTIF('Source checks'!$A$5:$A$33,"S10")+COUNTIF('Source checks'!$A$5:$A$33,"S11")+COUNTIF('Source checks'!$A$5:$A$33,"S12")+COUNTIF('Source checks'!$A$5:$A$33,"S13")+COUNTIF('Source checks'!$A$5:$A$33,"S14")+COUNTIF('Source checks'!$A$5:$A$33,"S15")+COUNTIF('Source checks'!$A$5:$A$33,"S16")+COUNTIF('Source checks'!$A$5:$A$33,"S17")+COUNTIF('Source checks'!$A$5:$A$33,"S18")+COUNTIF('Source checks'!$A$5:$A$33,"S19")+COUNTIF('Source checks'!$A$5:$A$33,"S20")+COUNTIF('Source checks'!$A$5:$A$33,"S21")+COUNTIF('Source checks'!$A$5:$A$33,"S22")+COUNTIF('Source checks'!$A$5:$A$33,"S23")+COUNTIF('Source checks'!$A$5:$A$33,"S24") -> 22 | C17: Field-specific source checks; not duplicate human appraisal | E17: Use the report and claim sheets to trace measured endpoints, sources, interpretation boundaries, and the next evidence needed. Unknown fields are not zero and observations are not automatically causal effects.
A18: Contemporary examples | B18: =COUNTIF('Source checks'!$A$5:$A$33,"U01")+COUNTIF('Source checks'!$A$5:$A$33,"U02")+COUNTIF('Source checks'!$A$5:$A$33,"U03")+COUNTIF('Source checks'!$A$5:$A$33,"U04") -> 4 | C18: Outside historical denominators
A19: Established frameworks | B19: =B20-B17-B18 -> 3 | C19: Proctor, NASSS, NICE
A20: All source-check records | B20: =COUNTA('Source checks'!A5:A33) -> 29 | C20: Different access levels
A23: Interpretive boundary
A24: Counts describe a fixed, non-exhaustive report corpus. Source checks are field-specific and were not duplicated by independent human reviewers. Sensitivity labels are not formal risk-of-bias ratings. The proposed worksheet is not independently validated. CSV data and analytical scripts are authoritative; workbook reproduction uses only the Python standard library.
A29: Reproduce: python 03_code/reproduce.py | Rebuild workbook: python 03_code/build_workbook.py | Tests: python -m unittest discover -s 03_code -p "test_*.py" -v

Sheet Core coding
A1: Core coding
A2: Source: 01_data/coding_revised_core22.csv. Report-level evidence; source-access limits and analytic roles are retained.
A4: study_id | B4: year | C4: title | D4: doi | E4: domain | F4: design_family | G4: geographic_context | H4: legacy_confidence | I4: role | J4: core_flag | K4: comparative | L4: user_outcome | M4: clinical_outcome | N4: safety_focused_investigation | O4: response_accuracy_benchmark | P4: referral_intention_proxy | Q4: health_system_operations | R4: patient_productivity | S4: source_url | T4: verification_status | U4: independent_human_review | V4: legacy_service_flag | W4: legacy_safety_flag | X4: legacy_org_flag
A5: S01 | B5: 2019 | C5: Physicians’ perceptions of chatbots in health care: cross-sectional web-based survey | D5: 10.2196/12887 | E5: General healthcare adoption/information | F5: Survey/observational | G5: United States | H5: Moderate | I5: bounded_healthcare_sample | J5: 1 | K5: 0 | L5: 1 | M5: 0 | N5: 0 | O5: 0 | P5: 0 | Q5: 0 | R5: 0 | S5: https://doi.org/10.2196/12887 | T5: Targeted current primary-source check; see source_verification_v2.csv for exact fields and access level. No independent human review. | U5: Not documented | V5: 0 | W5: 0 | X5: 0
A6: S02 | B6: 2019 | C6: Acceptability of artificial intelligence (AI)-led chatbot services in healthcare: a mixed-methods study | D6: 10.1177/2055207619871808 | E6: General healthcare adoption/information | F6: Mixed methods | G6: United Kingdom | H6: Moderate | I6: bounded_healthcare_sample | J6: 1 | K6: 0 | L6: 1 | M6: 0 | N6: 0 | O6: 0 | P6: 0 | Q6: 0 | R6: 0 | S6: https://doi.org/10.1177/2055207619871808 | T6: Targeted current primary-source check; see source_verification_v2.csv for exact fields and access level. No independent human review. | U6: Not documented | V6: 0 | W6: 0 | X6: 0
A7: S03 | B7: 2019 | C7: A chatbot system for mental healthcare based on SAT counseling method | D7: 10.1155/2019/9517321 | E7: Mental health and well-being | F7: Randomized/comparative intervention | G7: Japan | H7: Lower | I7: bounded_healthcare_sample | J7: 1 | K7: 1 | L7: 1 | M7: 1 | N7: 0 | O7: 0 | P7: 0 | Q7: 0 | R7: 0 | S7: https://doi.org/10.1155/2019/9517321 | T7: Targeted current primary-source check; specified fields/access level in source_verification_v2.csv; no independent human review. | U7: Not documented | V7: 0 | W7: 0 | X7: 0
A8: S04 | B8: 2019 | C8: Considering patient safety in autonomous e-mental health systems—detecting risk situations and referring patients back to human care | D8: 10.1186/s12911-019-0796-x | E8: Mental health and well-being | F8: Mixed methods | G8: Netherlands/online international sample | H8: Moderate | I8: bounded_healthcare_sample | J8: 1 | K8: 0 | L8: 1 | M8: 0 | N8: 1 | O8: 0 | P8: 1 | Q8: 0 | R8: 0 | S8: https://doi.org/10.1186/s12911-019-0796-x | T8: Targeted current primary-source check; see source_verification_v2.csv for exact fields and access level. No independent human review. | U8: Not documented | V8: 1 | W8: 1 | X8: 0
A9: S05 | B9: 2019 | C9: A chatbot versus physicians to provide information for patients with breast cancer: blind, randomized controlled noninferiority trial | D9: 10.2196/15787 | E9: Oncology information services | F9: Randomized/comparative intervention | G9: France | H9: Higher | I9: bounded_healthcare_sample | J9: 1 | K9: 1 | L9: 1 | M9: 0 | N9: 0 | O9: 0 | P9: 0 | Q9: 0 | R9: 0 | S9: https://doi.org/10.2196/15787 | T9: Targeted current primary-source check; see source_verification_v2.csv for exact fields and access level. No independent human review. | U9: Not documented | V9: 1 | W9: 1 | X9: 0
A10: S08 | B10: 2020 | C10: Physicians’ perceptions of the use of a chatbot for information seeking: qualitative study | D10: 10.2196/15185 | E10: General healthcare adoption/information | F10: Qualitative | G10: France | H10: Moderate | I10: bounded_healthcare_sample | J10: 1 | K10: 0 | L10: 1 | M10: 0 | N10: 0 | O10: 0 | P10: 0 | Q10: 0 | R10: 0 | S10: https://doi.org/10.2196/15185 | T10: Targeted current primary-source check; see source_verification_v2.csv for exact fields and access level. No independent human review. | U10: Not documented | V10: 0 | W10: 0 | X10: 0
A11: S09 | B11: 2020 | C11: Preliminary evaluation of the engagement and effectiveness of a mental health chatbot | D11: 10.3389/fdgth.2020.576361 | E11: Mental health and well-being | F11: Single-arm/pre-post intervention | G11: Brazil | H11: Lower | I11: bounded_healthcare_sample | J11: 1 | K11: 0 | L11: 1 | M11: 1 | N11: 0 | O11: 0 | P11: 0 | Q11: 0 | R11: 0 | S11: https://doi.org/10.3389/fdgth.2020.576361 | T11: Targeted current primary-source check; see source_verification_v2.csv for exact fields and access level. No independent human review. | U11: Not documented | V11: 1 | W11: 0 | X11: 0
A12: S10 | B12: 2020 | C12: AI-powered mental health chatbots: examining users’ motivations, active communicative action and engagement after mass-shooting disasters | D12: 10.1111/1468-5973.12319 | E12: Mental health and well-being | F12: Survey/observational | G12: United States | H12: Moderate | I12: bounded_healthcare_sample | J12: 1 | K12: 0 | L12: 1 | M12: 0 | N12: 0 | O12: 0 | P12: 0 | Q12: 0 | R12: 0 | S12: https://doi.org/10.1111/1468-5973.12319 | T12: Targeted current primary-source check; see source_verification_v2.csv for exact fields and access level. No independent human review. | U12: Not documented | V12: 0 | W12: 0 | X12: 0
A13: S11 | B13: 2020 | C13: Implementation of a digital chatbot to screen health system employees during the COVID-19 pandemic | D13: 10.1093/jamia/ocaa130 | E13: Public health | F13: Implementation/technical evaluation | G13: United States | H13: Moderate | I13: bounded_healthcare_sample | J13: 1 | K13: 0 | L13: 1 | M13: 0 | N13: 0 | O13: 0 | P13: 0 | Q13: 1 | R13: 0 | S13: https://doi.org/10.1093/jamia/ocaa130 | T13: Targeted current primary-source check; see source_verification_v2.csv for exact fields and access level. No independent human review. | U13: Not documented | V13: 1 | W13: 0 | X13: 1
A14: S12 | B14: 2021 | C14: A therapeutic relational agent for reducing problematic substance use (Woebot): development and usability study | D14: 10.2196/24850 | E14: Mental health and well-being | F14: Single-arm/pre-post intervention | G14: United States | H14: Lower | I14: bounded_healthcare_sample | J14: 1 | K14: 0 | L14: 1 | M14: 1 | N14: 0 | O14: 0 | P14: 0 | Q14: 0 | R14: 0 | S14: https://doi.org/10.2196/24850 | T14: Targeted current primary-source check; see source_verification_v2.csv for exact fields and access level. No independent human review. | U14: Not documented | V14: 1 | W14: 0 | X14: 0
A15: S13 | B15: 2021 | C15: Utilization of self-diagnosis health chatbots in real-world settings: case study | D15: 10.2196/19928 | E15: General healthcare adoption/information | F15: Survey/observational | G15: China | H15: Moderate | I15: bounded_healthcare_sample | J15: 1 | K15: 0 | L15: 1 | M15: 0 | N15: 0 | O15: 0 | P15: 0 | Q15: 0 | R15: 0 | S15: https://doi.org/10.2196/19928 | T15: Targeted current primary-source check; see source_verification_v2.csv for exact fields and access level. No independent human review. | U15: Not documented | V15: 1 | W15: 0 | X15: 0
A16: S14 | B16: 2021 | C16: Can chatbots help support a person’s mental health? Perceptions and views from mental healthcare professionals and experts | D16: 10.1145/3453175 | E16: Mental health and well-being | F16: Survey/observational | G16: Northern Ireland, Ireland, Scotland, Sweden and Finland | H16: Moderate | I16: bounded_healthcare_sample | J16: 1 | K16: 0 | L16: 1 | M16: 0 | N16: 0 | O16: 0 | P16: 0 | Q16: 0 | R16: 0 | S16: https://doi.org/10.1145/3453175 | T16: Targeted current primary-source check; specified fields/access level in source_verification_v2.csv; no independent human review. | U16: Not documented | V16: 0 | W16: 0 | X16: 0
... A26: S24 | B26: 2024 | C26: Development and evaluation of a smartphone-based chatbot coach to facilitate a balanced lifestyle in individuals with headaches (BalanceUP App): randomized controlled trial | D26: 10.2196/50132 | E26: Chronic-condition self-management | F26: Randomized/comparative intervention | G26: Switzerland | H26: Higher | I26: bounded_healthcare_sample | J26: 1 | K26: 1 | L26: 1 | M26: 1 | N26: 0 | O26: 0 | P26: 0 | Q26: 0 | R26: 1 | S26: https://doi.org/10.2196/50132 | T26: Targeted current primary-source check; see source_verification_v2.csv for exact fields and access level. No independent human review. | U26: Not documented | V26: 1 | W26: 0 | X26: 0

Sheet Report roster
A1: Report roster
A2: Source: 01_data/full_study_roster26.csv. Report-level evidence; source-access limits and analytic roles are retained.
A4: Study ID | B4: Citation | C4: Year | D4: Title | E4: DOI | F4: System | G4: Domain | H4: Country/region | I4: Stakeholder | J4: Design | K4: Design family | L4: Sample summary | M4: Comparator | N4: Duration/follow-up | O4: Interpretive confidence | P4: Source URL | Q4: Revised role | R4: Current verification | S4: Independent verification | T4: Full bibliographic citation | U4: Legacy reference number | V4: Legacy eligibility
A5: S01 | B5: Palanica et al. (2019) | C5: 2019 | D5: Physicians’ perceptions of chatbots in health care: cross-sectional web-based survey | E5: 10.2196/12887 | F5: Generic health chatbots (scenario-based) | G5: General healthcare adoption | H5: United States | I5: Physicians | J5: Cross-sectional web survey | K5: Survey/observational | L5: Recruited: 100; randomized: N/A; completed: 100; analyzed: 100 | M5: None | N5: Single survey | O5: Moderate | P5: https://doi.org/10.2196/12887 | Q5: bounded_healthcare_sample | R5: Targeted primary full text recheck, 23 October 2026: Results; Tables 1–6. Scope: 100 physician survey respondents; perceived task suitability and risks, not observed patient improvement. Not a full independent appraisal. | S5: Not documented | T5: Palanica A, Flaschner P, Thommandram A, Li M, Fossat Y. Physicians’ perceptions of chatbots in health care: cross-sectional web-based survey. J Med Internet Res. 2019;21(4):e12887. doi:10.2196/12887. | U5: [14] | V5: Working inclusion
A6: S02 | B6: Nadarzynski et al. (2019) | C6: 2019 | D6: Acceptability of artificial intelligence (AI)-led chatbot services in healthcare: a mixed-methods study | E6: 10.1177/2055207619871808 | F6: Generic health chatbot demonstration | G6: General healthcare adoption | H6: United Kingdom | I6: Potential healthcare users | J6: Mixed methods: interviews plus online survey | K6: Mixed methods | L6: 29 qualitative interviews; abstract survey N = 216; Results/Table 2 analyzed survey n = 215. Components are separate; participant totals are not pooled. | M6: None | N6: Single interview/survey | O6: Moderate | P6: https://doi.org/10.1177/2055207619871808 | Q6: bounded_healthcare_sample | R6: Targeted primary full text recheck, 23 October 2026: Results; quantitative sub-study; Table 2. Scope: 29 interviews; 215 analyzed survey respondents. Abstract mentions 216; the analyzed survey table uses 215. Not a full independent appraisal. | S6: Not documented | T6: Nadarzynski T, Miles O, Cowie A, Ridge D. Acceptability of artificial intelligence-led chatbot services in healthcare: a mixed-methods study. Digit Health. 2019;5:2055207619871808. doi:10.1177/2055207619871808. | U6: [41] | V6: Working inclusion
A7: S03 | B7: Kamita et al. (2019) | C7: 2019 | D7: A chatbot system for mental healthcare based on SAT counseling method | E7: 10.1155/2019/9517321 | F7: SAT counseling chatbot | G7: Mental health | H7: Japan | I7: Adult users | J7: Small randomized comparative experiment | K7: Randomized/comparative intervention | L7: 27 college students randomly assigned: chatbot n = 15; web control n = 12; one-session evaluation. | M7: Nonconversational web-based counseling information | N7: Single short-use session | O7: Lower | P7: https://doi.org/10.1155/2019/9517321 | Q7: bounded_healthcare_sample | R7: Targeted primary full text in publisher indexed record check, 23 October 2026: Sections 6.2–6.3; Table 3. 27 students randomly assigned 15/12; one-session SAT course; pre/post mental measures and TAM-based user motivation; not longitudinal use. No independent human duplicate assessment. | S7: Not documented | T7: Kamita, T., Ito, T., Matsumoto, A., Munakata, T. and Inoue, T., 2019. A chatbot system for mental healthcare based on SAT counseling method. Mobile Information Systems, 2019(1), p.9517321. https://doi.org/10.1155/2019/9517321 | U7: [60] | V7: Working inclusion
A8: S04 | B8: Tielman et al. (2019) | C8: 2019 | D8: Considering patient safety in autonomous e-mental health systems—detecting risk situations and referring patients back to human care | E8: 10.1186/s12911-019-0796-x | F8: Autonomous e-mental health virtual agent/referral scenarios | G8: Mental health safety and escalation | H8: Netherlands/online international sample | I8: Experts and potential users | J8: Formative qualitative study plus factorial vignette experiment | K8: Mixed methods | L8: Recruited: 8 experts; 229 online participants recruited; randomized: Factorial vignette assignment; completed: 160 online participants included; analyzed: 8 experts; 160 participants | M8: Alternative risk severity, agent response and referral strategies | N8: Single vignette experiment | O8: Moderate | P8: https://doi.org/10.1186/s12911-019-0796-x | Q8: bounded_healthcare_sample | R8: Targeted primary full text recheck, 23 October 2026: Experimental method; dependent measures. Scope: 160 participants in referral-intention experiment; intended self-referral, not verified completed referral. Not a full independent appraisal. | S8: Not documented | T8: Tielman ML, Neerincx MA, Pagliari C, Rizzo A, Brinkman WP. Considering patient safety in autonomous e-mental health systems: detecting risk situations and referring patients back to human care. BMC Med Inform Decis Mak. 2019;19:47. doi:10.1186/s12911-019-0796-x. | U8: [17] | V8: Working inclusion
A9: S05 | B9: Bibault et al. (2019) | C9: 2019 | D9: A chatbot versus physicians to provide information for patients with breast cancer: blind, randomized controlled noninferiority trial | E9: 10.2196/15787 | F9: Vik | G9: Oncology information service | H9: France | I9: Women with breast cancer | J9: Blind randomized noninferiority trial | K9: Randomized/comparative intervention | L9: Recruited: 142; randomized: 142 (71/71); completed: 142; analyzed: 142 | M9: Multidisciplinary physicians’ written answers | N9: Single information assessment | O9: Higher | P9: https://doi.org/10.2196/15787 | Q9: bounded_healthcare_sample | R9: Targeted primary full text recheck, 23 October 2026: Methods: Procedures/Outcomes; Results. Scope: 142 randomized 71/71; overall information-satisfaction noninferiority with 10% margin, 69% versus 64% success; predefined prechecked answers. Not a full independent appraisal. | S9: Not documented | T9: Bibault JE, Chaix B, Guillemassé A, et al. A chatbot versus physicians to provide information for patients with breast cancer: blind, randomized controlled noninferiority trial. J Med Internet Res. 2019;21(11):e15787. doi:10.2196/15787. | U9: [66] | V9: Working inclusion
A10: S06 | B10: Kocaballi et al. (2020) | C10: 2020 | D10: Responses of conversational agents to health and lifestyle prompts: investigation of appropriateness and presentation structures | E10: 10.2196/15823 | F10: Eight commercially available conversational agents | G10: Medical information and safety | H10: Australia-based research; global products | I10: Potential consumers | J10: Content/response evaluation | K10: Content/technical evaluation | L10: Recruited: 30 prompts; randomized: N/A; completed: 240 agent responses; analyzed: 240 responses | M10: Across agents and prompt categories | N10: Point-in-time test | O10: Moderate | P10: https://doi.org/10.2196/15823 | Q10: contextual_assistant_benchmark | R10: Targeted primary-source check in this revision | S10: Not documented | T10: Kocaballi AB, Quiroz JC, Rezazadegan D, et al. Responses of conversational agents to health and lifestyle prompts: investigation of appropriateness and presentation structures. J Med Internet Res. 2020;22(2):e15823. doi:10.2196/15823. | U10: [3] | V10: Working inclusion
A11: S07 | B11: Ferrand et al. (2020) | C11: 2020 | D11: Evaluating smart assistant responses for accuracy and misinformation regarding human papillomavirus vaccination: content analysis study | E11: 10.2196/19018 | F11: Four smart assistants | G11: Vaccination information | H11: United States | I11: Potential consumers | J11: Content analysis | K11: Content/technical evaluation | L11: Recruited: 10 questions across four assistants; randomized: N/A; completed: 103 analyzable responses; analyzed: 103 responses | M11: Across assistants/questions | N11: Point-in-time test | O11: Moderate | P11: https://doi.org/10.2196/19018 | Q11: contextual_assistant_benchmark | R11: Targeted primary-source check in this revision | S11: Not documented | T11: Ferrand J, Hockensmith R, Houghton RF, Walsh-Buhi ER. Evaluating smart assistant responses for accuracy and misinformation regarding human papillomavirus vaccination: content analysis study. J Med Internet Res. 2020;22(8):e19018. doi:10.2196/19018. | U11: [58] | V11: Working inclusion
A12: S08 | B12: Koman et al. (2020) | C12: 2020 | D12: Physicians’ perceptions of the use of a chatbot for information seeking: qualitative study | E12: 10.2196/15185 | F12: Information-seeking chatbot prototype | G12: Professional medical information | H12: France | I12: Physicians | J12: Qualitative interviews | K12: Qualitative | L12: Recruited: 10; randomized: N/A; completed: 10; analyzed: 8 general practitioners; 2 specialists | M12: None | N12: Single demonstration and interview | O12: Moderate | P12: https://doi.org/10.2196/15185 | Q12: bounded_healthcare_sample | R12: Targeted primary full text recheck, 23 October 2026: Results: Demographics; Discussion. Scope: 10 French healthcare professionals interviewed about information-seeking chatbot; qualitative user evidence. Not a full independent appraisal. | S12: Not documented | T12: Koman J, Fauvelle K, Schuck S, Texier N, Mebarki A. Physicians’ perceptions of the use of a chatbot for information seeking: qualitative study. J Med Internet Res. 2020;22(11):e15185. doi:10.2196/15185. | U12: [18] | V12: Working inclusion
A13: S09 | B13: Daley et al. (2020) | C13: 2020 | D13: Preliminary evaluation of the engagement and effectiveness of a mental health chatbot | E13: 10.3389/fdgth.2020.576361 | F13: Vitalk (Viki) | G13: Mental health | H13: Brazil | I13: Adult Portuguese-speaking users | J13: Uncontrolled real-world pre-post analysis | K13: Single-arm/pre-post intervention | L13: Retrospective completer cohort: 3,629 users completed the first 30-day program phase and were analyzed. Initial recruitment or installation denominator: not reported; not inferred from the completer cohort. No randomization. | M13: None | N13: 30-day first program phase | O13: Lower | P13: https://doi.org/10.3389/fdgth.2020.576361 | Q13: bounded_healthcare_sample | R13: Primary full text rechecked on 23 October 2026; 3,629 first-phase completers analyzed, not an enrollment denominator. Initial recruitment population not reported. | S13: Not documented | T13: Daley, K., Hungerbuehler, I., Cavanagh, K., Claro, H.G., Swinton, P.A. and Kapps, M., 2020. Preliminary evaluation of the engagement and effectiveness of a mental health chatbot. Frontiers in Digital Health, 2, 576361. https://doi.org/10.3389/fdgth.2020.576361 | U13: [68] | V13: Working inclusion
A14: S10 | B14: Cheng and Jiang (2020) | C14: 2020 | D14: AI-powered mental health chatbots: examining users’ motivations, active communicative action and engagement after mass-shooting disasters | E14: 10.1111/1468-5973.12319 | F14: AI-powered mental-health chatbot services | G14: Mental health/crisis communication | H14: United States | I14: Chatbot users | J14: Cross-sectional survey | K14: Survey/observational | L14: Recruited: 1,114; randomized: N/A; completed: 1,114; analyzed: 1,114 | M14: None | N14: Single survey | O14: Moderate | P14: https://doi.org/10.1111/1468-5973.12319 | Q14: bounded_healthcare_sample | R14: Targeted primary abstract recheck, 23 October 2026: Abstract. Scope: 1114 US participants surveyed; motivation, communication and engagement associations. Detailed attrition not re-extracted. Not a full independent appraisal. | S14: Not documented | T14: Cheng, Y. and Jiang, H., 2020. AI‐Powered mental health chatbots: Examining users’ motivations, active communicative action and engagement after mass‐shooting disasters. Journal of Contingencies and Crisis Management, 28(3), pp.339-354. https://doi.org/10.1111/1468-5973.12319 | U14: [61] | V14: Working inclusion
A15: S11 | B15: Judson et al. (2020) | C15: 2020 | D15: Implementation of a digital chatbot to screen health system employees during the COVID-19 pandemic | E15: 10.1093/jamia/ocaa130 | F15: COVID-19 employee screening chatbot | G15: Public health/occupational screening | H15: United States | I15: Health-system employees and occupational-health teams | J15: Implementation case study | K15: Implementation/technical evaluation | L15: Operational deployment; direct entrance-clearance timing: manual n = 28, digital n = 20. Mean clearance 48 versus 8 seconds; peak-shift mean queue 8 minutes 20 seconds versus 1 minute 40 seconds. | M15: Nonrandomized manual-versus-digital entrance-clearance comparison; peak-shift queue comparison during implementation. | N15: Initial pandemic deployment period | O15: Moderate | P15: https://doi.org/10.1093/jamia/ocaa130 | Q15: bounded_healthcare_sample | R15: Targeted primary full-text recheck, 23 October 2026: Results: Impact on Operations; Discussion: limitations. This is not independent duplicate human extraction. | S15: Not documented | T15: Judson TJ, Odisho AY, Young JJ, et al. Implementation of a digital chatbot to screen health system employees during the COVID-19 pandemic. J Am Med Inform Assoc. 2020;27(9):1450-1455. doi:10.1093/jamia/ocaa130. | U15: [38] | V15: Working inclusion
A16: S12 | B16: Prochaska et al. (2021) | C16: 2021 | D16: A therapeutic relational agent for reducing problematic substance use (Woebot): development and usability study | E16: 10.2196/24850 | F16: Woebot for Substance Use Disorders (W-SUDs) | G16: Mental health/substance use | H16: United States | I16: Adults with problematic substance use | J16: Single-group pre-post intervention | K16: Single-arm/pre-post intervention | L16: Recruited: 3,597 screened; 141 consented; 128 baseline; randomized: N/A; completed: 51 posttreatment respondents; analyzed: 101 analytic sample | M16: None | N16: 8 weeks | O16: Lower | P16: https://doi.org/10.2196/24850 | Q16: bounded_healthcare_sample | R16: Targeted primary full text recheck, 23 October 2026: Abstract; Results: Sample; Table 1. Scope: 101 analytic participants; 51 posttreatment respondents; eight-week single-group intervention with usability and symptom endpoints. Not a full independent appraisal. | S16: Not documented | T16: Prochaska, J.J., Vogel, E.A., Chieng, A., Kendra, M., Baiocchi, M., Pajarito, S. and Robinson, A., 2021. A therapeutic relational agent for reducing problematic substance use (Woebot): development and usability study. Journal of medical Internet research, 23(3), p.e24850. https://doi.org/10.2196/24850 | U16: [7] | V16: Working inclusion
... A30: S26 | B30: Siddals et al. (2024) | C30: 2024 | D30: “It happened to be the perfect thing”: experiences of generative AI chatbots for mental health | E30: 10.1038/s44184-024-00097-4 | F30: Generative AI chatbots used for mental-health support | G30: Mental health/user experience | H30: Self-selected/international; see source | I30: Consumer chatbot users | J30: Qualitative interviews | K30: Qualitative | L30: 19 interviewees | M30: None | N30: Cross-sectional | O30: Not newly appraised | P30: https://doi.org/10.1038/s44184-024-00097-4 | Q30: contextual_consumer_chatbot | R30: Targeted bibliographic/abstract verification | S30: Not documented | T30: Siddals, S., Torous, J. and Coxon, A., 2024. “It happened to be the perfect thing”: experiences of generative AI chatbots for mental health. npj Mental Health Research, 3, 48. https://doi.org/10.1038/s44184-024-00097-4 | U30: Contextual only | V30: Contextual

Sheet Extraction
A1: Extraction
A2: Source: 01_data/extraction_revised24.csv. Report-level evidence; source-access limits and analytic roles are retained.
A4: Study ID | B4: Citation | C4: Year | D4: System | E4: Modality | F4: Technical classification | G4: Domain | H4: Setting | I4: Country/region | J4: Stakeholder | K4: Design | L4: Recruitment | M4: Recruited N | N4: Randomized N | O4: Completed/endpoint N | P4: Analyzed N | Q4: Comparator | R4: Duration/follow-up | S4: Instruments | T4: User outcomes | U4: Service outcomes | V4: Organizational outcomes | W4: Clinical outcomes | X4: Safety/equity outcomes | Y4: Key limitations | Z4: Interpretive confidence | AA4: Source URL | AB4: Revised role | AC4: Correction note | AD4: Inherited reported findings | AE4: Legacy verification note | AF4: Current verification | AG4: Current source locator | AH4: Updated findings
A5: S01 | B5: Palanica et al. (2019) | C5: 2019 | D5: Generic health chatbots (scenario-based) | E5: Survey; no single deployed chatbot | F5: Not system-specific | G5: General healthcare adoption | H5: Practicing physicians | I5: United States | J5: Physicians | K5: Cross-sectional web survey | L5: Online physician survey | M5: 100 | O5: 100 | P5: 100 | Q5: None | R5: Single survey | S5: Study-specific perception questionnaire | T5: Perceived usefulness, limitations, risk and emotional capability | U5: Perceived suitability for scheduling, clinic location and medication information | V5: Professional acceptance and task-allocation preferences | W5: None measured | X5: Concern about incorrect self-diagnosis and inability to address all patient needs | Y5: Perception study; hypothetical use cases; no patient or service outcome measurement. | Z5: Moderate | AA5: https://doi.org/10.2196/12887 | AB5: bounded_healthcare_sample | AD5: Physicians viewed chatbots as more suitable for administrative or information tasks than for diagnosis, emotional support or complex care. | AE5: Publisher abstract/full text; sample, design and main task perceptions verified. | AF5: Targeted primary full text recheck, 23 October 2026: Results; Tables 1–6. Scope: 100 physician survey respondents; perceived task suitability and risks, not observed patient improvement. Not a full independent appraisal. | AG5: Results; Tables 1–6
A6: S02 | B6: Nadarzynski et al. (2019) | C6: 2019 | D6: Generic health chatbot demonstration | E6: Text chatbot demonstration plus interviews and online survey | F6: Not system-specific | G6: General healthcare adoption | H6: University/community internet users | I6: United Kingdom | J6: Potential healthcare users | K6: Mixed methods: interviews plus online survey | L6: University recruitment for interviews; social-media survey | M6: 29 interviews; survey abstract N = 216 | O6: 29 interviews; 215 survey respondents analyzed | P6: 244 across the two components | Q6: None | R6: Single interview/survey | S6: Semi-structured interview; 24-item survey | T6: Acceptability, perceived utility, trust, privacy/security and empathy concerns | U6: Willingness to use chatbots for information, appointment booking and service location | V6: Design requirements for uptake and person-centred implementation | W6: None measured | X6: Concerns about accuracy, cyber-security, confidentiality and lack of empathy | Y6: Convenience and social-media recruitment; largely hypothetical future use; exploratory unadjusted regressions. | Z6: Moderate | AA6: https://doi.org/10.1177/2055207619871808 | AB6: bounded_healthcare_sample | AD6: Sixty-seven percent of survey respondents were likely to use a health chatbot; perceived utility and trustworthiness were associated with acceptability, while poor IT skills and dislike of computer interaction were barriers. | AE6: Publisher full text; component samples, acceptability estimate and main predictors verified. | AF6: Targeted primary full text recheck, 23 October 2026: Results; quantitative sub-study; Table 2. Scope: 29 interviews; 215 analyzed survey respondents. Abstract mentions 216; the analyzed survey table uses 215. Not a full independent appraisal. | AG6: Results; quantitative sub-study; Table 2
A7: S03 | B7: Kamita et al. (2019) | C7: 2019 | D7: SAT counseling chatbot | E7: Web-based text chatbot | F7: Rule-based/SAT counseling dialogue | G7: Mental health | H7: Short experimental evaluation | I7: Japan | J7: College students | K7: Randomized comparative experiment, one session | L7: Convenience experimental sample | M7: 27 | N7: 27 (chatbot n = 15; web control n = 12); random assignment explicitly reported | O7: 27 | P7: Chatbot n = 15; web control n = 12 | Q7: Nonconversational web-based counseling information | R7: Single short-use session | S7: Self-esteem, state anxiety and depressive-symptom measures; technology acceptance items | T7: Ease of use, behavioral intention and interaction experience | U7: None directly measured | V7: None directly measured | W7: Short-term within-session changes in self-esteem, anxiety and depressive symptoms | X7: Not a safety study | Y7: Very small sample (n = 27) and one-session outcomes; random assignment is explicitly reported. Allocation concealment and sequence-generation details are not established in the available verification. | Z7: Lower | AA7: https://doi.org/10.1155/2019/9517321 | AB7: bounded_healthcare_sample | AC7: Random assignment is explicitly described; do not equate this with verified allocation concealment. Small sample and one-session follow-up remain limitations. | AD7: The chatbot group reported favorable short-term psychological and acceptance outcomes relative to its own baseline; the small sample prevents strong effectiveness conclusions. | AE7: Publisher full text; group sizes, design and short-term outcome domains verified. | AF7: Targeted primary full text in publisher indexed record check, 23 October 2026: Sections 6.2–6.3; Table 3. 27 students randomly assigned 15/12; one-session SAT course; pre/post mental measures and TAM-based user motivation; not longitudinal use. No independent human duplicate assessment.
A8: S04 | B8: Tielman et al. (2019) | C8: 2019 | D8: Autonomous e-mental health virtual agent/referral scenarios | E8: Virtual-agent vignettes | F8: Scenario-based referral strategies | G8: Mental health safety and escalation | H8: Expert interviews and crowdsourced vignette experiment | I8: Netherlands/online international sample | J8: Experts and potential users | K8: Formative qualitative study plus factorial vignette experiment | L8: Expert recruitment and Amazon Mechanical Turk | M8: 8 experts; 229 online participants recruited | N8: Factorial vignette assignment | O8: 160 online participants included | P8: 8 experts; 160 participants | Q8: Alternative risk severity, agent response and referral strategies | R8: Single vignette experiment | S8: Self-referral intention, intention to return and feeling heard | T8: Perceived support, return intention and referral intention | U8: Hypothetical intended referral, not completed handoff | V8: Human-care handoff strategy | W8: None measured | X8: Referral-intention proxy, not actual referral or harm | Y8: Vignette-based behavior, crowdsourced sample and no real clinical event or referral completion. | Z8: Moderate | AA8: https://doi.org/10.1186/s12911-019-0796-x | AB8: bounded_healthcare_sample | AC8: An empirical virtual-agent experiment measured intention to self-refer, not actual referral or avoided harm. | AD8: How the virtual agent communicated and referred users affected perceived support and willingness to seek or return to care; the evidence concerns hypothetical scenarios rather than deployed clinical outcomes. | AE8: Publisher full text; expert sample, recruited/analyzed online sample and factorial design verified. | AF8: Targeted primary full text recheck, 23 October 2026: Experimental method; dependent measures. Scope: 160 participants in referral-intention experiment; intended self-referral, not verified completed referral. Not a full independent appraisal. | AG8: Experimental method; dependent measures
A9: S05 | B9: Bibault et al. (2019) | C9: 2019 | D9: Vik | E9: Web-based text responses | F9: NLP/ML-supported oncology information chatbot | G9: Oncology information service | H9: Breast-cancer patient information | I9: France | J9: Women with breast cancer | K9: Blind randomized noninferiority trial | L9: Breast-cancer patient association | M9: 142 | N9: 142 (71/71) | O9: 142 | P9: 142 | Q9: Multidisciplinary physicians’ written answers | R9: Single information assessment | S9: Adapted EORTC QLQ-INFO25 | T9: Information satisfaction and perceived helpfulness | U9: Information satisfaction, not operational effectiveness | V9: Potential adjunct to clinician information workload; not directly measured | W9: None measured | X9: No direct safety/accuracy endpoint; information satisfaction | Y9: Predetermined questions and responses rather than natural live conversation; selected digitally literate population; no clinical outcome. | Z9: Higher | AA9: https://doi.org/10.2196/15787 | AB9: bounded_healthcare_sample | AC9: Primary endpoint is information satisfaction, not observed safety or response accuracy. | AD9: Success rates were 69% for Vik and 64% for physician answers, meeting the prespecified noninferiority criterion for the overall information-satisfaction outcome. | AE9: Publisher full text; randomization, completion, outcome and noninferiority result verified. | AF9: Targeted primary full text recheck, 23 October 2026: Methods: Procedures/Outcomes; Results. Scope: 142 randomized 71/71; overall information-satisfaction noninferiority with 10% margin, 69% versus 64% success; predefined prechecked answers. Not a full independent appraisal. | AG9: Methods: Procedures/Outcomes; Results
A10: S06 | B10: Kocaballi et al. (2020) | C10: 2020 | D10: Eight commercially available conversational agents | E10: Voice/text assistant responses | F10: Commercial general-purpose conversational agents | G10: Medical information and safety | H10: Standardized prompt evaluation | I10: Australia-based research; global products | J10: Potential consumers | K10: Content/response evaluation | L10: Not applicable | M10: 30 prompts | O10: 240 agent responses | P10: 240 responses | Q10: Across agents and prompt categories | R10: Point-in-time test | S10: Appropriateness and presentation-structure coding | T10: Not directly measured | U10: Appropriateness and presentation of responses | V10: None directly measured | W10: None measured | X10: Safety-critical response appropriateness | Y10: Point-in-time product test; no user behavior or clinical outcomes; results may change with software updates. | Z10: Moderate | AA10: https://doi.org/10.2196/15823 | AB10: contextual_assistant_benchmark | AC10: Apply the health-specific system/care-pathway rule consistently. | AD10: Only a minority of responses to safety-critical and lifestyle prompts were judged appropriate, showing that general-purpose agents should not be assumed to provide reliable health guidance. | AE10: Publisher full text; agents, prompt count, response count and appropriateness focus verified. | AF10: Targeted primary-source check in this revision
A11: S07 | B11: Ferrand et al. (2020) | C11: 2020 | D11: Four smart assistants | E11: Voice assistant responses | F11: Commercial smart assistants | G11: Vaccination information | H11: Standardized HPV-vaccine questions | I11: United States | J11: Potential consumers | K11: Content analysis | L11: Not applicable | M11: 10 questions across four assistants | O11: 103 analyzable responses | P11: 103 responses | Q11: Across assistants/questions | R11: Point-in-time test | S11: Accuracy and misinformation coding | T11: Not directly measured | U11: Accuracy of vaccination information | V11: None directly measured | W11: None measured | X11: Misinformation risk | Y11: No user behavior or clinical outcome; limited question set; product responses can change over time. | Z11: Moderate | AA11: https://doi.org/10.2196/19018 | AB11: contextual_assistant_benchmark | AC11: Assistant response accuracy is contextual benchmark evidence, not a dedicated healthcare-service intervention. | AD11: Across analyzed responses, 61.2% were accurate and 17.5% contained misinformation, indicating material information-safety limitations. | AE11: Publisher full text; question set, response count and accuracy/misinformation results verified. | AF11: Targeted primary-source check in this revision
A12: S08 | B12: Koman et al. (2020) | C12: 2020 | D12: Information-seeking chatbot prototype | E12: Text chatbot demonstration/interview | F12: Prototype conversational information tool | G12: Professional medical information | H12: Primary/specialist care physicians | I12: France | J12: Physicians | K12: Qualitative interviews | L12: Purposive physician recruitment | M12: 10 | O12: 10 | P12: 8 general practitioners; 2 specialists | Q12: None | R12: Single demonstration and interview | S12: Semi-structured interviews/thematic analysis | T12: Perceived usability, trust and information quality | U12: Potential professional information-seeking support | V12: Possible workflow fit and adoption requirements | W12: None measured | X12: Need for trustworthy and exhaustive responses | Y12: Small localized qualitative sample and prototype exposure; no implementation or performance outcomes. | Z12: Moderate | AA12: https://doi.org/10.2196/15185 | AB12: bounded_healthcare_sample | AD12: Physicians valued conversational tone and ergonomics but emphasized that professional adoption depends on exhaustive, reliable and transparent information. | AE12: Publisher full text; sample composition, design and principal themes verified. | AF12: Targeted primary full text recheck, 23 October 2026: Results: Demographics; Discussion. Scope: 10 French healthcare professionals interviewed about information-seeking chatbot; qualitative user evidence. Not a full independent appraisal. | AG12: Results: Demographics; Discussion
A13: S09 | B13: Daley et al. (2020) | C13: 2020 | D13: Vitalk (Viki) | E13: Instant-messenger text chatbot | F13: Scripted CBT/positive-psychology content with NLU triggers | G13: Mental health | H13: Real-world consumer use | I13: Brazil | J13: Adult Portuguese-speaking users | K13: Uncontrolled real-world pre-post analysis | L13: Voluntary users who installed Vitalk between June and November 2019; retrospective selection of first-phase completers | M13: Not reported; the initial installation/enrollment denominator is unavailable | N13: Not applicable (nonrandomized retrospective analysis) | O13: 3,629 first-phase (30-day) completers | P13: 3,629 completers; anxiety 1,648, depression 1,243, stress 738 | Q13: None | R13: 30-day first program phase | S13: GAD-7, PHQ-9, DASS-21 stress subscale; engagement rate | T13: Engagement and response frequency | U13: Scalable access to self-help content | V13: None directly measured | W13: Pre-post symptom change in anxiety, depression and stress | X13: Crisis-information module and human follow-up pathway described | Y13: Self-selected users, completer analysis, no control, limited demographic data and regression based on observational engagement. | Z13: Lower | AA13: https://doi.org/10.3389/fdgth.2020.576361 | AB13: bounded_healthcare_sample | AC13: 3,629 is the analyzed first-phase completer cohort, not the recruited population. The initial recruitment denominator is not reported. | AD13: Users completing a 30-day program phase showed large pre-post symptom reductions and higher engagement was associated with better anxiety and depression outcomes; without a control group, change cannot be attributed confidently to the chatbot. | AE13: Publisher full text; n = 3,629, 30-day exposure, measures and main pre-post results verified. | AF13: Primary full text rechecked on 23 October 2026: Abstract, Methods—Participants, and Results—Symptom Change; no initial recruitment denominator is reported. | AG13: Abstract; Methods—Participants; Results—Symptom Change
A14: S10 | B14: Cheng and Jiang (2020) | C14: 2020 | D14: AI-powered mental-health chatbot services | E14: User-reported chatbot use | F14: Multiple service platforms | G14: Mental health/crisis communication | H14: Post-disaster mental-health information context | I14: United States | J14: Chatbot users | K14: Cross-sectional survey | L14: Online panel/users with prior chatbot experience | M14: 1,114 | O14: 1,114 | P14: 1,114 | Q14: None | R14: Single survey | S14: Motivation, communicative action and engagement constructs | T14: Motivations, active communication and engagement | U14: Crisis-related information/support engagement | V14: Communication strategy implications | W14: None measured | X14: Sensitive post-disaster context; no clinical safety assessment | Y14: Cross-sectional self-report, retrospective platform use and no clinical outcome or verified usage logs. | Z14: Moderate | AA14: https://doi.org/10.1111/1468-5973.12319 | AB14: bounded_healthcare_sample | AD14: The study linked user motivations and active communicative behaviors with engagement in AI-powered mental-health chatbot services. | AE14: Publisher metadata/abstract and audited reference; sample and analytical focus verified. | AF14: Targeted primary abstract recheck, 23 October 2026: Abstract. Scope: 1114 US participants surveyed; motivation, communication and engagement associations. Detailed attrition not re-extracted. Not a full independent appraisal. | AG14: Abstract
A15: S11 | B15: Judson et al. (2020) | C15: 2020 | D15: COVID-19 employee screening chatbot | E15: Digital screening chatbot | F15: Rule-based screening and escalation workflow | G15: Public health/occupational screening | H15: Large academic health system | I15: United States | J15: Health-system employees and occupational-health teams | K15: Implementation case study | L15: Health-system deployment | M15: Pilot approximately 80 employees; system-wide rollout | O15: Entrance clearance: manual 28; digital 20; queue comparison at peak shift; different operational denominators. | P15: Manual 28 and digital 20 in timed entrance-clearance comparison; no pooled employee denominator. | Q15: Nonrandomized manual-versus-digital entrance-clearance comparison; peak-shift queue comparison during implementation. | R15: Initial pandemic deployment period | S15: Screening volume, workflow and escalation metrics | T15: Access and screening completion | U15: Manual 48 seconds versus digital 8 seconds clearance; peak queue 500 versus 100 seconds. | V15: Direct entrance-clearance and peak-queue timings; extrapolated waiting-hour savings; unquantified staffing/cost assertion. | W15: None evaluated comparatively | X15: Escalation pathways and screening criteria | Y15: Small nonrandomized timing samples; implementation-period confounding; no randomized or multisite A/B evaluation; no comprehensive quantified net-cost-effectiveness comparison. | Z15: Moderate | AA15: https://doi.org/10.1093/jamia/ocaa130 | AB15: bounded_healthcare_sample | AC15: Corrected omission of direct operational time measurements. Observed timings, extrapolated waiting-hour savings and an unquantified staffing/cost assertion are distinguished. | AD15: Observed entrance-clearance and queue times were lower with digital screening. The authors extrapolated more than 15,000 employee waiting hours saved and reported staffing/cost savings, but did not provide a comprehensive quantified net-cost-effectiveness comparison. | AE15: Publisher article/abstract and audited reference; implementation scale and purpose verified. | AF15: Targeted primary full-text recheck, 23 October 2026: Results: Impact on Operations; Discussion: limitations. This is not independent duplicate human extraction. | AG15: Results: Impact on Operations; Discussion: limitations | AH15: Observed entrance-clearance and queue times were lower with digital screening. The authors extrapolated more than 15,000 employee waiting hours saved and reported staffing/cost savings, but did not provide a comprehensive quantified net-cost-effectiveness comparison.
A16: S12 | B16: Prochaska et al. (2021) | C16: 2021 | D16: Woebot for Substance Use Disorders (W-SUDs) | E16: Mobile text relational agent | F16: Scripted therapeutic relational agent | G16: Mental health/substance use | H16: Remote consumer intervention | I16: United States | J16: Adults with problematic substance use | K16: Single-group pre-post intervention | L16: Online recruitment | M16: 3,597 screened; 141 consented; 128 baseline | O16: 51 posttreatment respondents | P16: 101 analytic sample | Q16: None | R16: 8 weeks | S16: Substance use, craving and mental-health self-report measures; usability | T16: Engagement, acceptability and usability | U16: Remote behavioral support feasibility | V16: None directly measured | W16: Pre-post substance-use and related symptom measures | X16: Remote intervention boundaries; no comparative safety evaluation | Y16: No comparator, high attrition, self-report and selected online sample. | Z16: Lower | AA16: https://doi.org/10.2196/24850 | AB16: bounded_healthcare_sample | AD16: Participants who remained in the study reported favorable pre-post changes and usability, but the single-group design and substantial attrition preclude firm effectiveness conclusions. | AE16: Publisher full text/abstract; screening, baseline, analytic and follow-up counts verified. | AF16: Targeted primary full text recheck, 23 October 2026: Abstract; Results: Sample; Table 1. Scope: 101 analytic participants; 51 posttreatment respondents; eight-week single-group intervention with usability and symptom endpoints. Not a full independent appraisal. | AG16: Abstract; Results: Sample; Table 1
A17: S13 | B17: Fan et al. (2021) | C17: 2021 | D17: DoctorBot | E17: Mobile self-diagnosis chatbot | F17: Symptom-input conversational system | G17: Medical information/self-diagnosis | H17: Real-world consumer use | I17: China | J17: Public users | K17: Retrospective real-world case study | L17: Routine users | M17: 16,519 users | O17: 47,684 consultation sessions | P17: 16,519 users / 47,684 sessions | Q17: None | R17: 6 months | S17: Usage logs and user feedback | T17: Utilization, dropout and user concerns | U17: Self-diagnosis consultation patterns | V17: Service design implications | W17: No validated diagnosis outcome in the review extraction | X17: Concerns about actionability and accuracy | Y17: Observational platform data, unclear representativeness and limited clinical ground truth. | Z17: Moderate | AA17: https://doi.org/10.2196/19928 | AB17: bounded_healthcare_sample | AD17: Large-scale usage data showed substantial use but also dropout and user concerns, emphasizing that utilization does not demonstrate diagnostic accuracy or clinical benefit. | AE17: Publisher abstract/full text; user and session counts, period and study purpose verified. | AF17: Targeted primary full text recheck, 23 October 2026: Methods; Results: Utilization. Scope: 16,519 users and 47,684 consultations over six months; usage outcomes do not establish clinical accuracy. Not a full independent appraisal. | AG17: Methods; Results: Utilization
A18: S14 | B18: Sweeney et al. (2021) | C18: 2021 | D18: Generic mental-health chatbots | E18: Professional survey | F18: Not system-specific | G18: Mental health service implementation | H18: Mental-health professional/expert survey | I18: Northern Ireland, Ireland, Scotland, Sweden and Finland | J18: Mental-health professionals and experts | K18: Cross-sectional survey | L18: Professional networks | M18: 100 | O18: 100 | P18: 100 | Q18: None | R18: Single survey | S18: Perception and implementation questionnaire | T18: Professional views of benefits, importance and limitations | U18: Perceived self-management and support potential | V18: Professional readiness and human-care boundaries | W18: None measured | X18: Strong concern about inability to understand emotion | Y18: Self-selected perception study; no deployment or outcome data. | Z18: Moderate | AA18: https://doi.org/10.1145/3453175 | AB18: bounded_healthcare_sample | AD18: Professionals perceived potential benefits and self-management value but emphasized limitations in emotional understanding and the need for human support. | AE18: Publisher abstract/full text; n = 100 and principal professional perceptions verified. | AF18: Targeted author-institution-hosted primary abstract check, 23 October 2026: Abstract. Online survey of mental healthcare professionals and experts; attitudes/perceptions, not a qualitative interview study or observed clinical effect. The inherited n = 100 was not separately re-extracted from full text here. No independent human duplicate assessment.
A19: S15 | B19: Rahman et al. (2021) | C19: 2021 | D19: AdolescentBot | E19: Text chatbot/prototype evaluation | F19: Contextualized conversational prototype | G19: Public health/sexual and reproductive health | H19: Adolescent information support | I19: Bangladesh | J19: Adolescents and medical personnel | K19: Mixed-method formative HCI study | L19: Participants from six regions | M19: 256 | O19: 256 responses/participants reported across study components; no longitudinal completion population established in accessible abstract. | P19: 256 | Q19: None | R19: Formative/prototype study | S19: Interviews, surveys and prototype feedback | T19: Information needs, acceptability and privacy/anonymity preferences | U19: Access to culturally appropriate SRH information | V19: Requirements for connection to trusted services | W19: None measured | X19: Stigma, language, culture and privacy in a low-resource context | Y19: Formative/prototype evidence; no clinical or longitudinal outcome. | Z19: Moderate | AA19: https://doi.org/10.1145/3411764.3445694 | AB19: bounded_healthcare_sample | AD19: The study identified culturally and socially specific requirements for adolescent SRH chatbots, including privacy, understandable language and trustworthy linkage to care. | AE19: Publisher paper/abstract and audited reference; sample, setting and formative focus verified. | AF19: Targeted primary abstract recheck, 23 October 2026: Abstract. Scope: Responses from 256 participants, including adolescents and medical personnel in six Bangladesh regions; prototype communication and experience analysis. Not a full independent appraisal. | AG19: Abstract
A20: S16 | B20: Griffin et al. (2021) | C20: 2021 | D20: Prospective hypertension self-management chatbot concept | E20: Interviews/design activities | F20: Not a deployed clinical chatbot | G20: Chronic-disease medication self-management | H20: Adults with hypertension | I20: United States | J20: Patients | K20: Mixed-method user-needs study | L20: Patient recruitment | M20: 15 | O20: 15 | P20: 15 | Q20: None | R20: Single study encounter | S20: Interviews, questionnaires and design probes | T20: Perceived usefulness, privacy, usability and information needs | U20: Medication refill, communication and accountability support needs | V20: Potential linkage to care teams | W20: None measured | X20: Privacy and information-overload concerns | Y20: Very small sample and concept-level evaluation; no deployed system or outcome. | Z20: Moderate | AA20: https://doi.org/10.1093/jamiaopen/ooab021 | AB20: bounded_healthcare_sample | AD20: Participants wanted medication-management, refill, communication and accountability support, while expressing privacy, usability and information-overload concerns. | AE20: Publisher article/abstract; sample, mixed-method design and principal needs verified. | AF20: Targeted primary full text recheck, 23 October 2026: Methods; Results: Sample characteristics. Scope: 15 participants with hypertension; mixed-method self-management needs and perceptions; not a treatment trial. Not a full independent appraisal. | AG20: Methods; Results: Sample characteristics
A21: S17 | B21: Jang et al. (2021) | C21: 2021 | D21: Todaki | E21: Mobile text chatbot | F21: CBT/psychoeducation chatbot | G21: Mental health/attention deficit | H21: Adult pilot intervention | I21: South Korea | J21: Adults with attention-deficit symptoms | K21: Pilot randomized feasibility/usability study | L21: Adult volunteer sample | M21: 46 | N21: 46 (23/23) | O21: Not established from accessible primary excerpt; randomized and ITT n must not be treated as completer n. | P21: ITT23/23=46; separate endpoint-completion denominator not established. | Q21: Information-only control | R21: 4 weeks | S21: Feasibility, usability and symptom/experience measures | T21: Usability, empathic/friendly character and dialogue naturalness | U21: Remote CBT/psychoeducation feasibility | V21: None directly measured | W21: Exploratory attention-related outcomes | X21: Not powered for safety | Y21: Small short pilot, limited power and no long-term service or clinical outcome. | Z21: Moderate | AA21: https://doi.org/10.1016/j.ijmedinf.2021.104440 | AB21: bounded_healthcare_sample | AD21: The pilot supported feasibility and identified valued empathic/friendly features, while unnatural conversational flow was a recurring limitation. | AE21: Publisher metadata/abstract and source audit; n = 46, group allocation, 4-week duration and usability themes verified. | AF21: Targeted primary abstract and publisher excerpts recheck, 23 October 2026: Abstract: Methods/Results. Scope: 46 randomized 23/23; four-week pilot; ITT analysis 23/23. Endpoint completer count was not established by the accessible excerpt. Not a full independent appraisal. | AG21: Abstract: Methods/Results | AH21: The small randomized pilot measured attention-deficit and associated symptoms plus usability; ITT group-by-time effects favored the intervention on selected attention-deficit scales. Feasibility evidence is not definitive effectiveness.
A22: S18 | B22: He et al. (2022) | C22: 2022 | D22: XiaoE | E22: Mobile/text mental-health chatbot | F22: CBT-informed conversational intervention | G22: Mental health/depressive symptoms | H22: Young-adult remote intervention | I22: China | J22: Young adults with depressive symptoms | K22: Single-blind three-arm randomized controlled trial | L22: Online/young-adult recruitment | M22: 148 | N22: 148: 49 XiaoE; 49 e-book; 50 Xiaoai | O22: Table 2 observed counts: day 7, 45/39/41 (total 125); day 30, 44/32/30 (total 106). | P22: ITT full randomized set with controlled multiple imputation; PP observed time-specific subsets. Table 2 displays endpoint n in both analyses; do not equate these with the full imputed ITT population. | Q22: Mental-health e-book and general chatbot Xiaoai. | R22: One-week intervention; assessment at day 7 and day 30 after enrollment. | S22: Depressive-symptom and user-experience measures | T22: Engagement, usability and perceived support | U22: Short-term remote mental-health support | V22: None directly measured | W22: Short-term depressive/distress outcomes | X22: Short duration; young-adult Chinese sample | Y22: Brief intervention and follow-up; attrition and missing-data assumptions; day-30 e-book comparison loses significance in sensitivity and PP analyses. | Z22: Higher | AA22: https://doi.org/10.2196/40719 | AB22: bounded_healthcare_sample | AC22: Replaced unfinished extraction instruction with verified time-specific observed counts. Kept randomized population, observed endpoint counts and imputed ITT analysis distinct. | AD22: Short-term PHQ-9 comparisons favored XiaoE. At day 30 the e-book comparison was not robust to missing-data sensitivity analysis and was nonsignificant in the per-protocol post-hoc test. Results depend on comparator, endpoint and analysis population. | AE22: Publisher abstract/full text and audited reference; design, arms and randomized sample verified. | AF22: Targeted primary full-text recheck, 23 October 2026: Methods: Statistical Analysis; Results: Table 2 and Table 3; PP Analysis. This is not independent duplicate human extraction. | AG22: Methods: Statistical Analysis; Results: Table 2 and Table 3; PP Analysis | AH22: Short-term PHQ-9 comparisons favored XiaoE. At day 30 the e-book comparison was not robust to missing-data sensitivity analysis and was nonsignificant in the per-protocol post-hoc test. Results depend on comparator, endpoint and analysis population.
A23: S19 | B23: Fitzsimmons-Craft et al. (2022) | C23: 2022 | D23: Tessa/StudentBodies-based chatbot | E23: Text-based prevention chatbot | F23: Structured CBT-based chatbot | G23: Mental health/eating-disorder prevention | H23: High-risk women | I23: United States | J23: Women at high risk for eating disorders | K23: Randomized clinical trial | L23: Online screening/recruitment | M23: 700 | N23: 700 (352 intervention; 348 control) | O23: Follow-up completion varied by time point | P23: Intention-to-treat/model-based analysis as reported | Q23: Waitlist control | R23: 3- and 6-month follow-up | S23: Weight/shape concerns, thin-ideal internalization, ED psychopathology, depression and anxiety | T23: Intervention use and engagement | U23: Scalable prevention delivery | V23: None directly measured | W23: ED risk factors, psychopathology and onset | X23: Women at elevated risk; attrition at follow-up | Y23: Follow-up attrition, waitlist rather than active control and restricted high-risk population. | Z23: Higher | AA23: https://doi.org/10.1002/eat.23662 | AB23: bounded_healthcare_sample | AD23: Compared with waitlist, the chatbot produced small reductions in weight/shape concerns at 3 and 6 months and short-term reduction in overall ED psychopathology; depression and anxiety did not differ. | AE23: Publisher full text; N = 700, comparator, follow-up and principal effect directions verified. | AF23: Targeted primary abstract recheck, 23 October 2026: Abstract: Method/Results. Scope: 700 randomized; weight/shape concerns improved at 3/6 months; no depression/anxiety between-group differences; exact endpoint completer counts not in abstract. Not a full independent appraisal. | AG23: Abstract: Method/Results
A24: S20 | B24: Durden et al. (2023) | C24: 2023 | D24: Woebot-LIFE | E24: Mobile relational agent | F24: Structured mental-health relational agent | G24: Mental health/stress and burnout | H24: Remote adult intervention | I24: United States | J24: Adults reporting stress/burnout | K24: Single-arm open-label intervention | L24: Online recruitment | M24: 256 | O24: Completion reported by time point | P24: 256 enrolled; analysis sets as reported | Q24: None | R24: 8 weeks | S24: Stress, burnout, resilience, PHQ-8 and GAD-7-related measures | T24: Engagement and acceptability | U24: Remote self-help support | V24: None directly measured | W24: Pre-post stress, burnout and resilience | X24: No controlled safety comparison | Y24: No comparator, self-selection, self-report and attrition. | Z24: Lower | AA24: https://doi.org/10.1016/j.invent.2023.100637 | AB24: bounded_healthcare_sample | AD24: Stress and burnout decreased and resilience increased over the intervention, but the uncontrolled open-label design does not establish that Woebot caused the changes. | AE24: Publisher abstract/full text and audited reference; n = 256, 8-week design and outcome domains verified. | AF24: Targeted primary abstract and publisher highlights recheck, 23 October 2026: Abstract; Highlights. Scope: 256 adults; eight-week relational-agent study; uncontrolled stress/burnout/resilience change, not established causal efficacy. Not a full independent appraisal. | AG24: Abstract; Highlights
A25: S21 | B25: Potts et al. (2023) | C25: 2023 | D25: ChatPal | E25: Multilingual mobile chatbot | F25: Rasa-based psychoeducational chatbot | G25: Mental health/public well-being | H25: Five European regions | I25: Ireland, Northern Ireland, Scotland, Finland and Sweden | J25: Adults from general population and mental-health service contexts | K25: Multicenter pre-post intervention | L25: Community and service recruitment | M25: 348 | O25: SWEMWBS baseline/mid/end 275/37/19; WHO-5 270/34/16; SWLS268/33/18. | P25: Instrument-specific available and paired analyses; 348 recruited is not a common baseline denominator. | Q25: No concurrent randomized comparator. | R25: 12 weeks | S25: SWEMWBS, WHO-5, SWLS and usage/experience data | T25: Engagement, usability and qualitative experience | U25: Multilingual psychoeducation and well-being support | V25: No direct organizational/workflow endpoint verified | W25: Well-being and life-satisfaction measures | X25: Multilingual regional deployment; technical barriers | Y25: Uncontrolled design, follow-up attrition and heterogeneous recruitment. | Z25: Moderate | AA25: https://doi.org/10.2196/43051 | AB25: bounded_healthcare_sample | AC25: Replaced the ambiguous 348-baseline and universal 19-completer wording with instrument-specific populations; no organizational-outcome recoding. | AD25: The study describes usage and participant feedback; standardized well-being changes were not statistically significant. Endpoint samples were small and differed by instrument. No direct provider-workload or organizational-cost endpoint was measured. | AE25: PubMed/publisher abstract; n = 348, 12-week design and nonsignificant primary well-being results verified. | AF25: Targeted primary full-text recheck, 23 October 2026: Results: Tables 2–4; User Feedback; Limitations. This is not independent duplicate human extraction. | AG25: Results: Tables 2–4; User Feedback; Limitations | AH25: The study describes usage and participant feedback; standardized well-being changes were not statistically significant. Endpoint samples were small and differed by instrument. No direct provider-workload or organizational-cost endpoint was measured.
A26: S22 | B26: Kleinau et al. (2024) | C26: 2024 | D26: Vitalk mental-wellbeing chatbot | E26: Mobile text chatbot | F26: Structured mental-wellbeing program | G26: Mental health/occupational well-being | H26: Healthcare workers | I26: Malawi | J26: Health workers | K26: Two-arm randomized controlled trial | L26: Health-worker recruitment | M26: 1,584 | N26: 1,584 | O26: 215 intervention and 296 control completed baseline/endline anxiety assessments; outcome-specific samples varied | P26: Outcome-specific complete cases/model analyses | Q26: Enhanced care as usual/passive information | R26: 8 weeks | S26: Depression, anxiety, burnout, resilience and resilience-activity measures | T26: Program participation/engagement | U26: Scalable support for health workers | V26: Occupational-wellbeing support in a low-resource health system | W26: Depression, anxiety, burnout and resilience | X26: LMIC implementation; substantial attrition | Y26: Major loss to follow-up and outcome-specific complete-case samples; pandemic context. | Z26: Moderate | AA26: https://doi.org/10.1371/journal.pone.0303370 | AB26: bounded_healthcare_sample | AD26: The trial found a statistically supported reduction in depression and increases in resilience-related outcomes; anxiety and burnout estimates were less certain. Attrition substantially reduced confidence. | AE26: Publisher full text; randomized N = 1,584, endpoint sample pattern and main estimates verified. | AF26: Targeted primary full text recheck, 23 October 2026: Abstract; Results: participant flow. Scope: 1,584 randomized; 215 treatment and 296 control completed baseline/endline anxiety assessments; outcome-specific attrition. Not a full independent appraisal. | AG26: Abstract; Results: participant flow
A27: S23 | B27: Langhammer et al. (2024) | C27: 2024 | D27: Aury plus digitized group intervention | E27: Chatbot followed by optional group program | F27: CBT-based stepped-care chatbot | G27: Mental health/general population | H27: Pandemic-era remote intervention | I27: Germany | J27: Adults in the general population | K27: Nonrandomized stepped-care pre/post evaluation with a within-subject waiting period; no concurrent randomized control | L27: Open/online recruitment | M27: 1,752 eligible/enrolled; 1,261 baseline | O27: 189 all-chatbot completers including 142 chatbot-only; 41 complete programme | P27: Outcome-specific; six-month 60 chatbot-only/27 complete programme | Q27: Within-subject four-week waiting period between components and observational program-use groups; no concurrent randomized allocation. | R27: 4-week chatbot plus optional 6-week group intervention | S27: Depression, anxiety and related mental-health measures | T27: Completion and stepped-care uptake | U27: Scalable stepped-care pathway | V27: Potential digital triage/stepped-care integration | W27: Pre-post mental-health symptom change | X27: Very high attrition | Y27: Uncontrolled design, very high attrition, completer analysis and pandemic context. | Z27: Lower | AA27: https://doi.org/10.1155/2024/8950388 | AB27: bounded_healthcare_sample | AC27: Distinct analysis populations must not be equated or summed. | AD27: Completers showed small-to-medium changes after the chatbot and larger changes after the full stepped-care program, but no control group and extreme attrition prevent causal interpretation. | AE27: Publisher full text; initial, post-chatbot and full-program samples and staged design verified. | AF27: Targeted primary full text in publisher indexed record check, 23 October 2026: Methods 2.1–2.5; Results; Table 1. 1,752 enrolled/eligible, 1,261 baseline; 189 complete chatbot records includes 142 chatbot-only; 41 complete-program records; 60/27 at 6 months. Nonrandomized stepped care with within-subject waiting period, not a concurrent randomized comparator. No independent human duplicate assessment.
A28: S24 | B28: Ulrich et al. (2024) | C28: 2024 | D28: BalanceUP | E28: Smartphone chatbot coach | F28: Personalized lifestyle coaching chatbot | G28: Chronic condition/headache self-management | H28: Adults with frequent headaches | I28: Switzerland | J28: Adults with headaches | K28: Randomized controlled trial | L28: Community/clinical recruitment | M28: 198 | N28: 198 (110 intervention; 88 waitlist) | O28: PP PHQ-ADS 78/72; MIDAS 71/67; denominators vary by endpoint. | P28: ITT mixed-model estimates and endpoint-specific PP subsets; no common completer n for all endpoints. | Q28: Waitlist; ITT mixed models and endpoint-specific per-protocol results. | R28: Intervention period reported in final article | S28: Well-being, headache-related and app-use measures | T28: Use, adherence and coaching experience | U28: Remote lifestyle support | V28: Participant work/school/household impairment; not health-system workflow | W28: Well-being and headache-related outcomes | X28: Attrition and selected smartphone users | Y28: Waitlist comparison, incomplete intervention completion and condition-specific population. | Z28: Higher | AA28: https://doi.org/10.2196/50132 | AB28: bounded_healthcare_sample | AC28: Added endpoint-specific participant productivity populations and retained separation from provider/health-system operations. | AD28: The report provides short-term patient-level mental-health/functioning evidence. PHQ-ADS per-protocol between-group d = -0.66 (95% CI -0.99 to -0.33); MIDAS d = -0.45 (95% CI -0.79 to -0.12). These are participant outcomes, not provider staffing savings. | AE28: Final journal article/abstract; N = 198, group sizes, completion and principal well-being result verified. | AF28: Targeted primary full-text recheck, 23 October 2026: Results: Table 3; Methods: outcome measures; Secondary Outcomes. This is not independent duplicate human extraction. | AG28: Results: Table 3; Methods: outcome measures; Secondary Outcomes | AH28: The report provides short-term patient-level mental-health/functioning evidence. PHQ-ADS per-protocol between-group d = -0.66 (95% CI -0.99 to -0.33); MIDAS d = -0.45 (95% CI -0.79 to -0.12). These are participant outcomes, not provider staffing savings.

Sheet Source checks
A1: Source checks
A2: Source: 01_data/source_verification_v2.csv. Report-level evidence; source-access limits and analytic roles are retained.
A4: record_id | B4: date | C4: source_url | D4: access_level | E4: source_locator | F4: verified_scope | G4: independent_human_review
A5: S01 | B5: 2026-10-23 | C5: https://www.jmir.org/2019/4/e12887/ | D5: Primary full text | E5: Results; Tables 1–6 | F5: 100 physician survey respondents; perceived task suitability and risks, not observed patient improvement. | G5: Not documented
A6: S02 | B6: 2026-10-23 | C6: https://journals.sagepub.com/doi/10.1177/2055207619871808 | D6: Primary full text | E6: Results; quantitative sub-study; Table 2 | F6: 29 interviews; 215 analyzed survey respondents. Abstract mentions 216; the analyzed survey table uses 215. | G6: Not documented
A7: S08 | B7: 2026-10-23 | C7: https://www.jmir.org/2020/11/e15185/ | D7: Primary full text | E7: Results: Demographics; Discussion | F7: 10 French healthcare professionals interviewed about information-seeking chatbot; qualitative user evidence. | G7: Not documented
A8: S09 | B8: 2026-10-23 | C8: https://www.frontiersin.org/journals/digital-health/articles/10.3389/fdgth.2020.576361/full | D8: Primary full text | E8: Abstract; Methods—Participants; Results—Symptom Change | F8: 3,629 first-phase completers analyzed: anxiety 1,648, depression 1,243, stress 738. Initial recruitment or installation denominator not reported; do not label completers as recruited. | G8: Not documented
A9: S10 | B9: 2026-10-23 | C9: https://onlinelibrary.wiley.com/doi/abs/10.1111/1468-5973.12319 | D9: Primary abstract | E9: Abstract | F9: 1114 US participants surveyed; motivation, communication and engagement associations. Detailed attrition not re-extracted. | G9: Not documented
A10: S12 | B10: 2026-10-23 | C10: https://www.jmir.org/2021/3/e24850/ | D10: Primary full text | E10: Abstract; Results: Sample; Table 1 | F10: 101 analytic participants; 51 posttreatment respondents; eight-week single-group intervention with usability and symptom endpoints. | G10: Not documented
A11: S13 | B11: 2026-10-23 | C11: https://www.jmir.org/2021/1/e19928/ | D11: Primary full text | E11: Methods; Results: Utilization | F11: 16,519 users and 47,684 consultations over six months; usage outcomes do not establish clinical accuracy. | G11: Not documented
A12: S15 | B12: 2026-10-23 | C12: https://dl.acm.org/doi/10.1145/3411764.3445694 | D12: Primary abstract | E12: Abstract | F12: Responses from 256 participants, including adolescents and medical personnel in six Bangladesh regions; prototype communication and experience analysis. | G12: Not documented
A13: S16 | B13: 2026-10-23 | C13: https://academic.oup.com/jamiaopen/article/4/2/ooab021/6236334 | D13: Primary full text | E13: Methods; Results: Sample characteristics | F13: 15 participants with hypertension; mixed-method self-management needs and perceptions; not a treatment trial. | G13: Not documented
A14: S17 | B14: 2026-10-23 | C14: https://doi.org/10.1016/j.ijmedinf.2021.104440 | D14: Primary abstract and publisher excerpts | E14: Abstract: Methods/Results | F14: 46 randomized 23/23; four-week pilot; ITT analysis 23/23. Endpoint completer count was not established by the accessible excerpt. | G14: Not documented
A15: S19 | B15: 2026-10-23 | C15: https://onlinelibrary.wiley.com/doi/abs/10.1002/eat.23662 | D15: Primary abstract | E15: Abstract: Method/Results | F15: 700 randomized; weight/shape concerns improved at 3/6 months; no depression/anxiety between-group differences; exact endpoint completer counts not in abstract. | G15: Not documented
... A33: S23 | B33: 2026-10-23 | C33: https://onlinelibrary.wiley.com/doi/abs/10.1155/2024/8950388 | D33: Primary full text in publisher indexed record | E33: Methods 2.1–2.5; Results; Table 1 | F33: 1,752 enrolled/eligible, 1,261 baseline; 189 complete chatbot records includes 142 chatbot-only; 41 complete-program records; 60/27 at 6 months. Nonrandomized stepped care with within-subject waiting period, not a concurrent randomized comparator. | G33: Not documented

Sheet Verified endpoints
A1: Verified endpoints
A2: Source: 01_data/verified_endpoints.csv. Report-level evidence; source-access limits and analytic roles are retained.
A4: record_id | B4: endpoint | C4: group | D4: n | E4: value | F4: unit | G4: timepoint | H4: note
A5: S11 | B5: entrance_clearance | C5: manual | D5: 28 | E5: 48 | F5: seconds | G5: implementation observation | H5: Observed mean; nonrandomized
A6: S11 | B6: entrance_clearance | C6: digital | D6: 20 | E6: 8 | F6: seconds | G6: implementation observation | H6: Observed mean; nonrandomized
A7: S11 | B7: peak_shift_queue | C7: before | E7: 500 | F7: seconds | G7: peak shift | H7: Reported mean; sample not specified
A8: S11 | B8: peak_shift_queue | C8: after | E8: 100 | F8: seconds | G8: peak shift | H8: Reported mean; sample not specified
A9: S18 | B9: PHQ9_population | C9: XiaoE | D9: 49 | F9: participants | G9: randomized | H9: Observed endpoint counts and full randomized ITT with imputation are distinct
A10: S18 | B10: PHQ9_population | C10: ebook | D10: 49 | F10: participants | G10: randomized | H10: Observed endpoint counts and full randomized ITT with imputation are distinct
A11: S18 | B11: PHQ9_population | C11: Xiaoai | D11: 50 | F11: participants | G11: randomized | H11: Observed endpoint counts and full randomized ITT with imputation are distinct
A12: S18 | B12: PHQ9_population | C12: XiaoE | D12: 45 | F12: participants | G12: day7_observed | H12: Observed endpoint counts and full randomized ITT with imputation are distinct
A13: S18 | B13: PHQ9_population | C13: ebook | D13: 39 | F13: participants | G13: day7_observed | H13: Observed endpoint counts and full randomized ITT with imputation are distinct
A14: S18 | B14: PHQ9_population | C14: Xiaoai | D14: 41 | F14: participants | G14: day7_observed | H14: Observed endpoint counts and full randomized ITT with imputation are distinct
A15: S18 | B15: PHQ9_population | C15: XiaoE | D15: 44 | F15: participants | G15: day30_observed | H15: Observed endpoint counts and full randomized ITT with imputation are distinct
A16: S18 | B16: PHQ9_population | C16: ebook | D16: 32 | F16: participants | G16: day30_observed | H16: Observed endpoint counts and full randomized ITT with imputation are distinct
A17: S18 | B17: PHQ9_population | C17: Xiaoai | D17: 30 | F17: participants | G17: day30_observed | H17: Observed endpoint counts and full randomized ITT with imputation are distinct

Sheet Claim dispositions
A1: Claim dispositions
A2: Source: 01_data/claim_dispositions18.csv. Report-level evidence; source-access limits and analytic roles are retained.
A4: assessment_id | B4: case_id | C4: report_id | D4: claim | E4: disposition | F4: rationale | G4: source_url | H4: source_locator | I4: access_level | J4: assessor
A5: CE01A | B5: CE01 | C5: S05 | D5: The curated-answer comparison met its prespecified overall information-satisfaction noninferiority criterion. | E5: Supported within tested conditions | F5: 142 participants; 69% versus 64%; 10% margin; fixed prechecked information, not autonomous dialogue. | G5: https://www.jmir.org/2019/11/e15787/ | H5: Methods: procedures/outcomes; no actual conversation per question | I5: Primary full text; targeted endpoint check | J5: Single analytical workflow; no independent reliability claim
A6: CE01B | B6: CE01 | C6: S05 | D6: The same evidence establishes safety of unrestricted autonomous oncology advice. | E6: Not established | F6: Information satisfaction does not identify autonomous conversational safety. | G6: https://www.jmir.org/2019/11/e15787/ | H6: Methods: procedures/outcomes; no actual conversation per question | I6: Primary full text; targeted endpoint check | J6: Single analytical workflow; no independent reliability claim
A7: CE02A | B7: CE02 | C7: S04 | D7: The experiment provides evidence about intended self-referral under the studied interaction conditions. | E7: Supported with qualifications | F7: An intention proxy in 160 participants; not completed clinical behaviour. | G7: https://link.springer.com/article/10.1186/s12911-019-0796-x | H7: Abstract; Experimental method; dependent measures | I7: Primary full text; targeted endpoint check | J7: Single analytical workflow; no independent reliability claim
A8: CE02B | B8: CE02 | C8: S04 | D8: The source establishes effective real-world crisis handoff. | E8: Not established | F8: Completed referral and downstream safety were not verified by the intention endpoint. | G8: https://link.springer.com/article/10.1186/s12911-019-0796-x | H8: Abstract; Experimental method; dependent measures | I8: Primary full text; targeted endpoint check | J8: Single analytical workflow; no independent reliability claim
A9: CE03A | B9: CE03 | C9: S21 | D9: ChatPal generated engagement and feedback data alongside inconclusive well-being changes. | E9: Supported with qualifications | F9: Uncontrolled study with severe, instrument-specific attrition. | G9: https://www.jmir.org/2023/1/e43051/ | H9: Results: Tables 2–4; User Feedback; Limitations | I9: Primary full text; targeted endpoint check | J9: Single analytical workflow; no independent reliability claim
A10: CE03B | B10: CE03 | C10: S21 | D10: Provider-cost consequences of ChatPal have been evaluated in this claim ledger. | E10: Not assessed | F10: No provider-cost extraction is available for this case; no favorable or unfavorable economic conclusion is assigned. | G10: https://www.jmir.org/2023/1/e43051/ | H10: Results: Tables 2–4; User Feedback; Limitations | I10: Primary full text; targeted endpoint check | J10: Single analytical workflow; no independent reliability claim
A11: CE04A | B11: CE04 | C11: S11 | D11: Digital screening had lower observed clearance and queue times in the reported implementation comparison. | E11: Supported with qualifications | F11: 48 versus 8 seconds (n = 28/20); queue 500 versus 100 seconds; nonrandomized small timing samples. | G11: https://pmc.ncbi.nlm.nih.gov/articles/PMC7313990/ | H11: Results: Impact on Operations; limitations | I11: Primary full text rechecked 23 October 2026; observed, extrapolated and asserted outcomes distinguished | J11: Single analytical workflow; no independent reliability claim
A12: CE04B | B12: CE04 | C12: S11 | D12: These timings establish net cost-effectiveness across health systems. | E12: Not established | F12: Time savings are real observed endpoints; comprehensive net costs and a transportable counterfactual are not supplied. | G12: https://pmc.ncbi.nlm.nih.gov/articles/PMC7313990/ | H12: Results: Impact on Operations; limitations | I12: Primary full text rechecked 23 October 2026; observed, extrapolated and asserted outcomes distinguished | J12: Single analytical workflow; no independent reliability claim
A13: CE05A | B13: CE05 | C13: S24 | D13: The BalanceUP trial provides patient-level mental-health and productivity outcome evidence. | E13: Supported with qualifications | F13: Separate PHQ-ADS and MIDAS denominators; comparator and attrition constrain transfer. | G13: https://www.jmir.org/2024/1/e50132/ | H13: Table 3; Methods: MIDAS; Secondary Outcomes | I13: Primary full text; targeted endpoint check | J13: Single analytical workflow; no independent reliability claim
A14: CE05B | B14: CE05 | C14: S24 | D14: The provider can reduce clinical staffing because participant MIDAS scores improved. | E14: Not established | F14: Patient absenteeism/presenteeism and provider workload have different analytical units. | G14: https://www.jmir.org/2024/1/e50132/ | H14: Table 3; Methods: MIDAS; Secondary Outcomes | I14: Primary full text; targeted endpoint check | J14: Single analytical workflow; no independent reliability claim
A15: CE06A | B15: CE06 | C15: U01 | D15: The randomized messaging experiment estimates usage-intention responses in the tested population. | E15: Supported within tested conditions | F15: 1000 adults; scenario-based descriptions and normative messages; not longitudinal adoption. | G15: https://www.jmir.org/2026/1/e97773/ | H15: Abstract; Methods; usage-intention measures | I15: Primary full text; targeted current check | J15: Single analytical workflow; no independent reliability claim
... A22: CE09B | B22: CE09 | C22: U04 | D22: Treatment randomization establishes a causal mediating effect of therapeutic alliance. | E22: Not established | F22: Treatment allocation does not randomize the mediator; identification assumptions require separate justification. | G22: https://jamanetwork.com/journals/jamanetworkopen/fullarticle/2847751 | H22: Abstract; Results; structural equation associations | I22: Primary full text; targeted current check | J22: Single analytical workflow; no independent reliability claim

Sheet Worked cases
A1: Worked cases
A2: Source: 01_data/claim_evidence_ledger9.csv. Report-level evidence; source-access limits and analytic roles are retained.
A4: case_id | B4: report_id | C4: citation | D4: doi | E4: observed_endpoint | F4: unit_population | G4: comparator | H4: supported_inference | I4: illustrative_stronger_claim | J4: failed_or_unresolved_checks | K4: additional_evidence_required | L4: source_locator | M4: source_url | N4: verification_level | O4: interpretive_status | P4: primary_claim | Q4: primary_disposition | R4: secondary_claim | S4: secondary_disposition | T4: assessment_ids
A5: CE01 | B5: S05 | C5: Bibault et al. (2019) | D5: 10.2196/15787 | E5: Information satisfaction for predefined, prechecked answers | F5: 142 patients; two randomized groups | G5: Physician-generated answers | H5: A bounded information-satisfaction comparison | I5: The chatbot provides generally safe autonomous cancer advice | J5: Construct; transferability | K5: Direct safety/accuracy outcomes and evaluation of actual open-ended deployment | L5: Methods: procedures/outcomes; no actual conversation per question | M5: https://www.jmir.org/2019/11/e15787/ | N5: Primary full text; targeted endpoint check | O5: Analyst-proposed worked example; stronger claim is not a quotation or allegation about source authors. | P5: The curated-answer comparison met its prespecified overall information-satisfaction noninferiority criterion. | Q5: Supported within tested conditions | R5: The same evidence establishes safety of unrestricted autonomous oncology advice. | S5: Not established | T5: CE01A;CE01B
A6: CE02 | B6: S04 | C6: Tielman et al. (2019) | D6: 10.1186/s12911-019-0796-x | E6: Intended self-referral after scenario-based interaction | F6: 160 online participants | G6: Virtual-agent strategies and scenarios | H6: Agent strategy affects referral intention in the experiment | I6: The system safely completes crisis referrals | J6: Construct; transferability; governance | K6: Observed handoff completion, time to access and adverse consequences in real care | L6: Abstract; Experimental method; dependent measures | M6: https://link.springer.com/article/10.1186/s12911-019-0796-x | N6: Primary full text; targeted endpoint check | O6: Analyst-proposed worked example; stronger claim is not a quotation or allegation about source authors. | P6: The experiment provides evidence about intended self-referral under the studied interaction conditions. | Q6: Supported with qualifications | R6: The source establishes effective real-world crisis handoff. | S6: Not established | T6: CE02A;CE02B
A7: CE03 | B7: S21 | C7: Potts et al. (2023) | D7: 10.2196/43051 | E7: Well-being, engagement and user feedback | F7: 348 recruited; SWEMWBS 275/37/19, WHO-5 270/34/16, SWLS 268/33/18 at baseline/mid/end | G7: No randomized concurrent comparator | H7: A feasibility/engagement account with inconclusive well-being change | I7: Deployment improves healthcare-organization performance | J7: Unit; attribution | K7: Direct organizational workload/cost measures and suitable comparison | L7: Results: Tables 2–4; User Feedback; Limitations | M7: https://www.jmir.org/2023/1/e43051/ | N7: Primary full text; targeted endpoint check | O7: Analyst-proposed worked example; stronger claim is not a quotation or allegation about source authors. | P7: ChatPal generated engagement and feedback data alongside inconclusive well-being changes. | Q7: Supported with qualifications | R7: Provider-cost consequences of ChatPal have been evaluated in this claim ledger. | S7: Not assessed | T7: CE03A;CE03B
A8: CE04 | B8: S11 | C8: Judson et al. (2020) | D8: 10.1093/jamia/ocaa130 | E8: Entrance clearance: manual 48 s (n = 28) versus digital 8 s (n = 20); peak-shift queue 500 s versus 100 s. Authors extrapolated >15,000 waiting hours saved and reported staffing/cost savings without a comprehensive quantified net-cost model. | F8: Employees at one health system; timed clearance samples n = 28 manual and n = 20 digital | G8: Nonrandomized manual-versus-digital timing and implementation-period queue comparison | H8: Observed local operational time-saving evidence; not merely usage. Causal attribution and net organizational economics remain bounded. | I8: The implementation has established generalizable net cost-effectiveness. | J8: Attribution; transferability; full economic scope | K8: A credible counterfactual, total implementation/oversight/maintenance costs, displaced and added work, and setting-specific economic analysis. | L8: Results: Impact on Operations; limitations | M8: https://pmc.ncbi.nlm.nih.gov/articles/PMC7313990/ | N8: Primary full text rechecked 23 October 2026; observed, extrapolated and asserted outcomes distinguished | O8: Analyst-proposed worked example; stronger claim is not a quotation or allegation about source authors. | P8: Digital screening had lower observed clearance and queue times in the reported implementation comparison. | Q8: Supported with qualifications | R8: These timings establish net cost-effectiveness across health systems. | S8: Not established | T8: CE04A;CE04B
A9: CE05 | B9: S24 | C9: Ulrich et al. (2024) | D9: 10.2196/50132 | E9: Patient PHQ-ADS and MIDAS outcomes; PP PHQ-ADS 78/72; MIDAS 71/67; MIDAS between-group d = -0.45 (95% CI -0.79 to -0.12) | F9: 198 randomized participants; endpoint-specific patient subsets | G9: Waitlist; ITT mixed models and PP analyses | H9: Patient symptom/functioning and productivity evidence within this trial; not provider staffing or health-system workload | I9: The provider needs fewer clinical staff | J9: Unit; construct | K9: Provider staffing/workflow endpoints rather than patient impairment scales | L9: Table 3; Methods: MIDAS; Secondary Outcomes | M9: https://www.jmir.org/2024/1/e50132/ | N9: Primary full text; targeted endpoint check | O9: Analyst-proposed worked example; stronger claim is not a quotation or allegation about source authors. | P9: The BalanceUP trial provides patient-level mental-health and productivity outcome evidence. | Q9: Supported with qualifications | R9: The provider can reduce clinical staffing because participant MIDAS scores improved. | S9: Not established | T9: CE05A;CE05B
A10: CE06 | B10: U01 | C10: Liao et al. (2026) | D10: 10.2196/97773 | E10: Usage intention after randomized messaging descriptions | F10: 1000 US adults; online experiment | G10: Message framing and described chatbot type | H10: Adoption-related belief/intention evidence | I10: The chatbot achieves sustained adoption and clinical benefit | J10: Construct; transferability | K10: Observed longitudinal use and clinical endpoints | L10: Abstract; Methods; usage-intention measures | M10: https://www.jmir.org/2026/1/e97773/ | N10: Primary full text; targeted current check | O10: Analyst-proposed worked example; stronger claim is not a quotation or allegation about source authors. | P10: The randomized messaging experiment estimates usage-intention responses in the tested population. | Q10: Supported within tested conditions | R10: The study establishes sustained chatbot adoption and clinical benefit. | S10: Not established | T10: CE06A;CE06B
A11: CE07 | B11: U02 | C11: Sompornpailin et al. (2026) | D11: 10.2196/86149 | E11: Unscheduled hospital visits over 12 weeks | F11: 40 patients; 20 per arm | G11: Chatbot plus usual care versus usual care | H11: Feasibility and an imprecise preliminary service-use comparison | I11: The intervention has established lower emergency utilization | J11: Attribution; uncertainty | K11: Larger adequately powered comparison; preserve P = .24 and endpoint definition | L11: Abstract; Unscheduled hospital visits: 3/20 vs 7/20, P = .24 | M11: https://formative.jmir.org/2026/1/e86149/ | N11: Primary full text; targeted current check | O11: Analyst-proposed worked example; stronger claim is not a quotation or allegation about source authors. | P11: The pilot demonstrates that the chatbot reduces unscheduled hospital visits. | Q11: Not established | R11: The report supports a bounded feasibility assessment of the supportive oncology platform. | S11: Supported with qualifications | T11: CE07A;CE07B
A12: CE08 | B12: U03 | C12: Heinz et al. (2025) | D12: 10.1056/AIoa2400802 | E12: Symptoms following a generative therapy intervention | F12: 210 adults randomized: 106 Therabot / 104 waitlist | G12: Waitlist, not active clinician-delivered therapy | H12: The primary abstract reports symptom benefits versus waitlist at 4/8 weeks; no full-text effect re-extraction or clinician-equivalence inference | I12: Therabot is equivalent to clinician-delivered therapy | J12: Attribution; transferability | K12: Active clinician comparator with an appropriate prespecified design | L12: Primary-author-hosted abstract: Methods and Results | M12: https://www.nicholasjacobson.com/publication/heinz-mackin-trudeau-bhattacharya-wang-et-al-2025/ | N12: Publication abstract reproduced on senior author website; publisher full text inaccessible | O12: Analyst-proposed worked example; stronger claim is not a quotation or allegation about source authors. | P12: Therabot improved reported symptoms relative to waitlist in the trial described by the primary abstract. | Q12: Supported with qualifications | R12: Its comparative effectiveness against clinician-delivered treatment was assessed here. | S12: Not assessed | T12: CE08A;CE08B
A13: CE09 | B13: U04 | C13: Shoshani et al. (2026) | D13: 10.1001/jamanetworkopen.2026.6713 | E13: Symptoms, well-being and therapeutic-alliance associations | F13: 995 university students | G13: Group therapy and waiting list | H13: Some comparative clinical benefits; examined alliance/engagement associations | I13: Randomization proves alliance causally mediates benefit | J13: Attribution | K13: A justified mediation design and assumptions; treatment randomization does not randomize the mediator | L13: Abstract; Results; structural equation associations | M13: https://jamanetwork.com/journals/jamanetworkopen/fullarticle/2847751 | N13: Primary full text; targeted current check | O13: Analyst-proposed worked example; stronger claim is not a quotation or allegation about source authors. | P13: The three-arm trial provides outcome-specific clinical comparisons, including anxiety benefit against both comparators. | Q13: Supported with qualifications | R13: Treatment randomization establishes a causal mediating effect of therapeutic alliance. | S13: Not established | T13: CE09A;CE09B

Sheet Framework comparison
A1: Framework comparison
A2: Source: 01_data/framework_comparison.csv. Report-level evidence; source-access limits and analytic roles are retained.
A4: framework | B4: key | C4: established_contribution | D4: overlap | E4: added_application | F4: not_claimed | G4: source_url
A5: Proctor implementation outcomes | B5: proctor | C5: Separates implementation from service and clinical outcomes; addresses measurement and unit of analysis. | D5: Construct and unit checks already have an established methodological basis. | E5: Record exactly which published endpoint supports a specified chatbot deployment claim and which inference remains unmeasured. | F5: No new outcome taxonomy; no replacement for Proctor outcome definitions. | G5: https://doi.org/10.1007/s10488-010-0319-7
A6: NASSS | B6: nasss | C6: Examines complexity across condition, technology, value proposition, adopters, organization, wider context and adaptation over time. | D6: Transferability, governance and value proposition are central to NASSS already. | E6: Attach source-level claim dispositions to a particular proposed task, model version, population and support pathway. | F6: Not a substitute for longitudinal contextual/implementation analysis; no superiority claim. | G6: https://www.jmir.org/2017/11/e367/
A7: NICE Evidence Standards Framework | B7: nice | C7: Specifies intended-purpose/risk-proportionate evidence and clinical, resource, budget-impact and economic evaluation expectations. | D7: Comparator, organizational value, monitoring and cost requirements are already specified in the standard. | E7: Use a claim-to-source worksheet to check whether the cited result actually addresses the benefit asserted in a procurement discussion. | F7: Not a new evidence standard, medical-device approval or certification; does not determine applicable jurisdiction. | G7: https://www.nice.org.uk/corporate/ecd7
A8: Present claim–evidence alignment worksheet | B8: present | C8: Proposed application-layer synthesis illustrated by 9 cases and 18 analyst-specified claims. | D8: Uses established inference, implementation and evidence-standard principles. | E8: Five checks plus explicit evidence disposition, source locator and next observation; clinical and organizational outcomes remain parallel. | F8: No empirical validation, reliability coefficient, prevalence estimate or demonstrated decision advantage. | G8: Supplement S1; claim_dispositions18.csv

Sheet Contemporary reports
A1: Contemporary reports
A2: Source: 01_data/currency_evidence.csv. Report-level evidence; source-access limits and analytic roles are retained.
A4: record_id | B4: year | C4: citation | D4: doi | E4: source_url | F4: finding | G4: boundary
A5: U01 | B5: 2026 | C5: Liao Y, Madeo A, Allen CG, et al. The Impact of Chatbot Type and Normative Messaging on Chatbot Usage Intention Based on the Health Technology Acceptance Model: Randomized Controlled Trial. J Med Internet Res. 2026;28:e97773. | D5: 10.2196/97773 | E5: https://www.jmir.org/2026/1/e97773/ | F5: 1000 US adults; 4x2 online scenario experiment; usage intention, not actual sustained use or clinical efficacy. | G5: Purposively selected contemporary illustration; not part of historical denominator or an exhaustive update.
A6: U02 | B6: 2026 | C6: Sompornpailin N, Susiriwatananont T, Sriuranpong V, et al. Feasibility and Preliminary Effectiveness of the ChulaCancer Mobile Chatbot for Supportive Care of Patients With Breast or Colorectal Cancer Receiving Chemotherapy: Pilot Randomized Controlled Trial. JMIR Form Res. 2026;10:e86149. | D6: 10.2196/86149 | E6: https://formative.jmir.org/2026/1/e86149/ | F6: 40 patients; 20/20; 12-week pilot; unscheduled hospital visits 3/20 versus 7/20, P = .24, not established reduction. | G6: Purposively selected contemporary illustration; not part of historical denominator or an exhaustive update.
A7: U03 | B7: 2025 | C7: Heinz MV, Mackin DM, Trudeau BM, et al. Randomized trial of a generative AI chatbot for mental health treatment. NEJM AI. 2025;2(4):AIoa2400802. | D7: 10.1056/AIoa2400802 | E7: https://www.nicholasjacobson.com/publication/heinz-mackin-trudeau-bhattacharya-wang-et-al-2025/ | F7: 210 adults; Therabot versus waitlist; symptom improvement at four/eight weeks; not an active clinician-treatment comparison. | G7: Primary-publication abstract reproduced by a study author; publisher full text inaccessible. Only sample, comparator, timing and abstract-level outcome direction used; no complete risk-of-bias assessment.
A8: U04 | B8: 2026 | C8: Shoshani A, Gurfinkel B, Kor A, et al. Efficacy of a conversational AI agent for psychiatric symptoms and digital therapeutic alliance: a randomized clinical trial. JAMA Netw Open. 2026;9(4):e266713. | D8: 10.1001/jamanetworkopen.2026.6713 | E8: https://jamanetwork.com/journals/jamanetworkopen/fullarticle/2847751 | F8: 995 university students; 12-week three-arm trial with group therapy and waiting list; some symptom/well-being benefits; no PTSD difference; alliance/engagement/outcome associations examined. | G8: Contemporary counterexample to a blanket absence-of-mechanism-evidence claim; associations do not themselves establish randomized mediation. Not in historical denominator.

Sheet Theory examples
A1: Theory examples
A2: Source: 01_data/theory_examples.csv. Report-level evidence; source-access limits and analytic roles are retained.
A4: study_id | B4: framework | C4: role | D4: source_locator | E4: source_url | F4: interpretation
A5: S18 | B5: CBT | C5: Intervention content | D5: Primary report Abstract; Intervention | E5: https://www.jmir.org/2022/11/e40719/ | F5: Selected positive example; not a theory-frequency observation
A6: S21 | B6: PERMA/H | C6: Positive-psychology content design | D6: Primary report Intervention | E6: https://www.jmir.org/2023/1/e43051/ | F6: Selected positive example; not a theory-frequency observation
A7: S24 | B7: HAPA | C7: Behaviour-change stage measurement | D7: Table 2 footnote; Table 3 | E7: https://www.jmir.org/2024/1/e50132/ | F7: Selected positive example; not a theory-frequency observation

Sheet References
A1: References
A2: Source: 04_outputs/main_reference_crosswalk.csv. Report-level evidence; source-access limits and analytic roles are retained.
A4: number | B4: key | C4: doi | D4: reference | E4: source_url
A5: 1 | B5: wutz | C5: 10.2196/46548 | D5: Wutz M, Hermes M, Winter V, Köberlein-Neu J. Factors influencing the acceptability, acceptance, and adoption of conversational agents in health care: integrative review. J Med Internet Res. 2023;25:e46548. doi:10.2196/46548. | E5: https://doi.org/10.2196/46548
A6: 2 | B6: laymouna | C6: 10.2196/56930 | D6: Laymouna M, Ma Y, Lessard D, Schuster T, Engler K, Lebouché B. Roles, users, benefits, and limitations of chatbots in health care: rapid review. J Med Internet Res. 2024;26:e56930. doi:10.2196/56930. | E6: https://doi.org/10.2196/56930
A7: 3 | B7: jabir | C7: 10.2196/44548 | D7: Jabir AI, Martinengo L, Lin X, Torous J, Subramaniam M, Tudor Car L. Evaluating conversational agents for mental health: scoping review of outcomes and outcome measurement instruments. J Med Internet Res. 2023;25:e44548. doi:10.2196/44548. | E7: https://doi.org/10.2196/44548
A8: 4 | B8: proctor | C8: 10.1007/s10488-010-0319-7 | D8: Proctor E, Silmere H, Raghavan R, et al. Outcomes for implementation research: conceptual distinctions, measurement challenges, and research agenda. Adm Policy Ment Health. 2011;38(2):65–76. doi:10.1007/s10488-010-0319-7. | E8: https://doi.org/10.1007/s10488-010-0319-7
A9: 5 | B9: nasss | C9: 10.2196/jmir.8775 | D9: Greenhalgh T, Wherton J, Papoutsi C, et al. Beyond adoption: a new framework for theorizing and evaluating nonadoption, abandonment, and challenges to the scale-up, spread, and sustainability of health and care technologies. J Med Internet Res. 2017;19(11):e367. doi:10.2196/jmir.8775. | E9: https://www.jmir.org/2017/11/e367/
A10: 6 | B10: nice | D10: National Institute for Health and Care Excellence. Evidence standards framework for digital health technologies. ECD7. Updated 9 August 2022. https://www.nice.org.uk/corporate/ecd7 (accessed 23 October 2026). | E10: https://www.nice.org.uk/corporate/ecd7
A11: 7 | B11: whittemore | C11: 10.1111/j.1365-2648.2005.03621.x | D11: Whittemore R, Knafl K. The integrative review: updated methodology. J Adv Nurs. 2005;52(5):546–553. doi:10.1111/j.1365-2648.2005.03621.x. | E11: https://doi.org/10.1111/j.1365-2648.2005.03621.x
A12: 8 | B12: sanra | C12: 10.1186/s41073-019-0064-8 | D12: Baethge C, Goldbeck-Wood S, Mertens S. SANRA—a scale for the quality assessment of narrative review articles. Res Integr Peer Rev. 2019;4:5. doi:10.1186/s41073-019-0064-8. | E12: https://doi.org/10.1186/s41073-019-0064-8
A13: 9 | B13: kocaballi | C13: 10.2196/15823 | D13: Kocaballi AB, Quiroz JC, Rezazadegan D, et al. Responses of conversational agents to health and lifestyle prompts: investigation of appropriateness and presentation structures. J Med Internet Res. 2020;22(2):e15823. doi:10.2196/15823. | E13: https://doi.org/10.2196/15823
A14: 10 | B14: ferrand | C14: 10.2196/19018 | D14: Ferrand J, Hockensmith R, Houghton RF, Walsh-Buhi ER. Evaluating smart assistant responses for accuracy and misinformation regarding human papillomavirus vaccination: content analysis study. J Med Internet Res. 2020;22(8):e19018. doi:10.2196/19018. | E14: https://doi.org/10.2196/19018
A15: 11 | B15: maples | C15: 10.1038/s44184-023-00047-6 | D15: Maples B, Cerit M, Vishwanath A, Pea R. Loneliness and suicide mitigation for students using GPT3-enabled chatbots. npj Ment Health Res. 2024;3:4. doi:10.1038/s44184-023-00047-6. | E15: https://doi.org/10.1038/s44184-023-00047-6
A16: 12 | B16: siddals | C16: 10.1038/s44184-024-00097-4 | D16: Siddals S, Torous J, Coxon A. “It happened to be the perfect thing”: experiences of generative AI chatbots for mental health. npj Ment Health Res. 2024;3:48. doi:10.1038/s44184-024-00097-4. | E16: https://doi.org/10.1038/s44184-024-00097-4
A17: 13 | B17: bibault | C17: 10.2196/15787 | D17: Bibault JE, Chaix B, Guillemassé A, et al. A chatbot versus physicians to provide information for patients with breast cancer: blind, randomized controlled noninferiority trial. J Med Internet Res. 2019;21(11):e15787. doi:10.2196/15787. | E17: https://doi.org/10.2196/15787
A18: 14 | B18: potts | C18: 10.2196/43051 | D18: Potts C, Lindström F, Bond R, et al. A multilingual digital mental health and well-being chatbot (ChatPal): pre-post multicenter intervention study. J Med Internet Res. 2023;25:e43051. doi:10.2196/43051. | E18: https://doi.org/10.2196/43051
A19: 15 | B19: tielman | C19: 10.1186/s12911-019-0796-x | D19: Tielman ML, Neerincx MA, Pagliari C, Rizzo A, Brinkman WP. Considering patient safety in autonomous e-mental health systems: detecting risk situations and referring patients back to human care. BMC Med Inform Decis Mak. 2019;19:47. doi:10.1186/s12911-019-0796-x. | E19: https://doi.org/10.1186/s12911-019-0796-x
A20: 16 | B20: palanica | C20: 10.2196/12887 | D20: Palanica A, Flaschner P, Thommandram A, Li M, Fossat Y. Physicians’ perceptions of chatbots in health care: cross-sectional web-based survey. J Med Internet Res. 2019;21(4):e12887. doi:10.2196/12887. | E20: https://doi.org/10.2196/12887
A21: 17 | B21: nadarzynski | C21: 10.1177/2055207619871808 | D21: Nadarzynski T, Miles O, Cowie A, Ridge D. Acceptability of artificial intelligence-led chatbot services in healthcare: a mixed-methods study. Digit Health. 2019;5:2055207619871808. doi:10.1177/2055207619871808. | E21: https://doi.org/10.1177/2055207619871808
A22: 18 | B22: koman | C22: 10.2196/15185 | D22: Koman J, Fauvelle K, Schuck S, Texier N, Mebarki A. Physicians’ perceptions of the use of a chatbot for information seeking: qualitative study. J Med Internet Res. 2020;22(11):e15185. doi:10.2196/15185. | E22: https://doi.org/10.2196/15185
... A34: 30 | B34: chula | C34: 10.2196/86149 | D34: Sompornpailin N, Susiriwatananont T, Sriuranpong V, et al. Feasibility and Preliminary Effectiveness of the ChulaCancer Mobile Chatbot for Supportive Care of Patients With Breast or Colorectal Cancer Receiving Chemotherapy: Pilot Randomized Controlled Trial. JMIR Form Res. 2026;10:e86149. doi:10.2196/86149. | E34: https://doi.org/10.2196/86149

Sheet Sensitivity
A1: Sensitivity
A2: Source: 04_outputs/sensitivity_results.csv. Report-level evidence; source-access limits and analytic roles are retained.
A4: scenario | B4: n | C4: user_n | D4: clinical_n | E4: safety_related_n | F4: operations_n | G4: interpretation | H4: user_pct | I4: clinical_pct | J4: safety_related_pct | K4: operations_pct
A5: Legacy24 (superseded; not a final result) | B5: 24 | C5: 22 | D5: 11 | E5: 4 | F5: 2 | G5: Old misclassification retained for traceability only | H5: 91.7 | I5: 45.8 | J5: 16.7 | K5: 8.3
A6: Corrected24 including generic benchmarks | B6: 24 | C6: 22 | D6: 11 | E6: 3 | F6: 1 | G6: Report counts only; not pooled effects or safety certification | H6: 91.7 | I6: 45.8 | J6: 12.5 | K6: 4.2
A7: Healthcare-specific22 | B7: 22 | C7: 22 | D7: 11 | E7: 1 | F7: 1 | G7: Report counts only; not pooled effects or safety certification | H7: 100 | I7: 50 | J7: 4.5 | K7: 4.5
A8: Core excluding inherited Lower labels | B8: 17 | C8: 17 | D8: 6 | E8: 1 | F8: 1 | G8: Report counts only; not pooled effects or safety certification | H8: 100 | I8: 35.3 | J8: 5.9 | K8: 5.9
A9: Core excluding referral-intention proxy | B9: 21 | C9: 21 | D9: 11 | E9: 0 | F9: 1 | G9: Report counts only; not pooled effects or safety certification | H9: 100 | I9: 52.4 | J9: 0 | K9: 4.8
A10: Expanded26 including consumer context | B10: 26 | C10: 24 | D10: 11 | E10: 3 | F10: 1 | G10: Consumer perceived benefit is not coded as clinical efficacy | H10: 92.3 | I10: 42.3 | J10: 11.5 | K10: 3.8

Sheet Leave one out
A1: Leave one out
A2: Source: 04_outputs/leave_one_out.csv. Report-level evidence; source-access limits and analytic roles are retained.
A4: removed_id | B4: n | C4: mental | D4: comparative | E4: user_outcome | F4: clinical_outcome | G4: safety_focused_investigation | H4: health_system_operations | I4: patient_productivity | J4: mental_pct | K4: comparative_pct | L4: user_outcome_pct | M4: clinical_outcome_pct | N4: safety_focused_investigation_pct | O4: health_system_operations_pct | P4: patient_productivity_pct
A5: S01 | B5: 21 | C5: 13 | D5: 7 | E5: 21 | F5: 11 | G5: 1 | H5: 1 | I5: 1 | J5: 61.9 | K5: 33.3 | L5: 100 | M5: 52.4 | N5: 4.8 | O5: 4.8 | P5: 4.8
A6: S02 | B6: 21 | C6: 13 | D6: 7 | E6: 21 | F6: 11 | G6: 1 | H6: 1 | I6: 1 | J6: 61.9 | K6: 33.3 | L6: 100 | M6: 52.4 | N6: 4.8 | O6: 4.8 | P6: 4.8
A7: S03 | B7: 21 | C7: 12 | D7: 6 | E7: 21 | F7: 10 | G7: 1 | H7: 1 | I7: 1 | J7: 57.1 | K7: 28.6 | L7: 100 | M7: 47.6 | N7: 4.8 | O7: 4.8 | P7: 4.8
A8: S04 | B8: 21 | C8: 12 | D8: 7 | E8: 21 | F8: 11 | G8: 0 | H8: 1 | I8: 1 | J8: 57.1 | K8: 33.3 | L8: 100 | M8: 52.4 | N8: 0 | O8: 4.8 | P8: 4.8
A9: S05 | B9: 21 | C9: 13 | D9: 6 | E9: 21 | F9: 11 | G9: 1 | H9: 1 | I9: 1 | J9: 61.9 | K9: 28.6 | L9: 100 | M9: 52.4 | N9: 4.8 | O9: 4.8 | P9: 4.8
A10: S08 | B10: 21 | C10: 13 | D10: 7 | E10: 21 | F10: 11 | G10: 1 | H10: 1 | I10: 1 | J10: 61.9 | K10: 33.3 | L10: 100 | M10: 52.4 | N10: 4.8 | O10: 4.8 | P10: 4.8
A11: S09 | B11: 21 | C11: 12 | D11: 7 | E11: 21 | F11: 10 | G11: 1 | H11: 1 | I11: 1 | J11: 57.1 | K11: 33.3 | L11: 100 | M11: 47.6 | N11: 4.8 | O11: 4.8 | P11: 4.8
A12: S10 | B12: 21 | C12: 12 | D12: 7 | E12: 21 | F12: 11 | G12: 1 | H12: 1 | I12: 1 | J12: 57.1 | K12: 33.3 | L12: 100 | M12: 52.4 | N12: 4.8 | O12: 4.8 | P12: 4.8
A13: S11 | B13: 21 | C13: 13 | D13: 7 | E13: 21 | F13: 11 | G13: 1 | H13: 0 | I13: 1 | J13: 61.9 | K13: 33.3 | L13: 100 | M13: 52.4 | N13: 4.8 | O13: 0 | P13: 4.8
A14: S12 | B14: 21 | C14: 12 | D14: 7 | E14: 21 | F14: 10 | G14: 1 | H14: 1 | I14: 1 | J14: 57.1 | K14: 33.3 | L14: 100 | M14: 47.6 | N14: 4.8 | O14: 4.8 | P14: 4.8
A15: S13 | B15: 21 | C15: 13 | D15: 7 | E15: 21 | F15: 11 | G15: 1 | H15: 1 | I15: 1 | J15: 61.9 | K15: 33.3 | L15: 100 | M15: 52.4 | N15: 4.8 | O15: 4.8 | P15: 4.8
A16: S14 | B16: 21 | C16: 12 | D16: 7 | E16: 21 | F16: 11 | G16: 1 | H16: 1 | I16: 1 | J16: 57.1 | K16: 33.3 | L16: 100 | M16: 52.4 | N16: 4.8 | O16: 4.8 | P16: 4.8
... A26: S24 | B26: 21 | C26: 13 | D26: 6 | E26: 21 | F26: 10 | G26: 1 | H26: 1 | I26: 0 | J26: 61.9 | K26: 28.6 | L26: 100 | M26: 47.6 | N26: 4.8 | O26: 4.8 | P26: 0

Sheet Outcome co-occurrence
A1: Outcome co-occurrence
A2: Source: 04_outputs/outcome_cooccurrence.csv. Report-level evidence; source-access limits and analytic roles are retained.
A4: outcome_a | B4: outcome_b | C4: co_measured_n | D4: denominator | E4: percent | F4: report_ids | G4: interpretation
A5: user_outcome | B5: clinical_outcome | C5: 11 | D5: 22 | E5: 50 | F5: S03; S09; S12; S17; S18; S19; S20; S21; S22; S23; S24 | G5: Co-measurement only; no tested mediation or causal linkage inferred
A6: user_outcome | B6: safety_focused_investigation | C6: 1 | D6: 22 | E6: 4.5 | F6: S04 | G6: Co-measurement only; no tested mediation or causal linkage inferred
A7: user_outcome | B7: health_system_operations | C7: 1 | D7: 22 | E7: 4.5 | F7: S11 | G7: Co-measurement only; no tested mediation or causal linkage inferred
A8: user_outcome | B8: patient_productivity | C8: 1 | D8: 22 | E8: 4.5 | F8: S24 | G8: Co-measurement only; no tested mediation or causal linkage inferred
A9: clinical_outcome | B9: safety_focused_investigation | C9: 0 | D9: 22 | E9: 0 | G9: Co-measurement only; no tested mediation or causal linkage inferred
A10: clinical_outcome | B10: health_system_operations | C10: 0 | D10: 22 | E10: 0 | G10: Co-measurement only; no tested mediation or causal linkage inferred
A11: clinical_outcome | B11: patient_productivity | C11: 1 | D11: 22 | E11: 4.5 | F11: S24 | G11: Co-measurement only; no tested mediation or causal linkage inferred
A12: safety_focused_investigation | B12: health_system_operations | C12: 0 | D12: 22 | E12: 0 | G12: Co-measurement only; no tested mediation or causal linkage inferred
A13: safety_focused_investigation | B13: patient_productivity | C13: 0 | D13: 22 | E13: 0 | G13: Co-measurement only; no tested mediation or causal linkage inferred
A14: health_system_operations | B14: patient_productivity | C14: 0 | D14: 22 | E14: 0 | G14: Co-measurement only; no tested mediation or causal linkage inferred
